{
  "target_date": "20240517",
  "race_count": 45,
  "races": [
    {
      "race_key": "20240517_函館_1R",
      "開催日": "20240517",
      "競輪場コード": "11",
      "競輪場名": "函館",
      "開催名": "能登半島支援・五稜郭杯争奪戦",
      "グレード": "G3",
      "レース番号": 1,
      "周長(m)": 400,
      "みなし直線(m)": 51.3,
      "カント角(度)": 30.6142,
      "レース種別": "Ｓ級選抜",
      "距離": 2025,
      "周回数": 5,
      "発走時刻": "14:50",
      "投票締切": "14:47",
      "天候": "曇",
      "風速": "3.0"
    },
    {
      "race_key": "20240517_函館_2R",
      "開催日": "20240517",
      "競輪場コード": "11",
      "競輪場名": "函館",
      "開催名": "能登半島支援・五稜郭杯争奪戦",
      "グレード": "G3",
      "レース番号": 2,
      "周長(m)": 400,
      "みなし直線(m)": 51.3,
      "カント角(度)": 30.6142,
      "レース種別": "Ｓ級選抜",
      "距離": 2025,
      "周回数": 5,
      "発走時刻": "15:17",
      "投票締切": "15:14",
      "天候": "曇",
      "風速": "3.0"
    },
    {
      "race_key": "20240517_函館_3R",
      "開催日": "20240517",
      "競輪場コード": "11",
      "競輪場名": "函館",
      "開催名": "能登半島支援・五稜郭杯争奪戦",
      "グレード": "G3",
      "レース番号": 3,
      "周長(m)": 400,
      "みなし直線(m)": 51.3,
      "カント角(度)": 30.6142,
      "レース種別": "Ｓ級選抜",
      "距離": 2025,
      "周回数": 5,
      "発走時刻": "15:45",
      "投票締切": "15:42",
      "天候": "曇",
      "風速": "3.0"
    },
    {
      "race_key": "20240517_函館_4R",
      "開催日": "20240517",
      "競輪場コード": "11",
      "競輪場名": "函館",
      "開催名": "能登半島支援・五稜郭杯争奪戦",
      "グレード": "G3",
      "レース番号": 4,
      "周長(m)": 400,
      "みなし直線(m)": 51.3,
      "カント角(度)": 30.6142,
      "レース種別": "Ｓ級選抜",
      "距離": 2025,
      "周回数": 5,
      "発走時刻": "16:15",
      "投票締切": "16:12",
      "天候": "曇",
      "風速": "3.0"
    },
    {
      "race_key": "20240517_函館_5R",
      "開催日": "20240517",
      "競輪場コード": "11",
      "競輪場名": "函館",
      "開催名": "能登半島支援・五稜郭杯争奪戦",
      "グレード": "G3",
      "レース番号": 5,
      "周長(m)": 400,
      "みなし直線(m)": 51.3,
      "カント角(度)": 30.6142,
      "レース種別": "Ｓ級選抜",
      "距離": 2025,
      "周回数": 5,
      "発走時刻": "16:45",
      "投票締切": "16:42",
      "天候": "曇",
      "風速": "3.0"
    },
    {
      "race_key": "20240517_函館_6R",
      "開催日": "20240517",
      "競輪場コード": "11",
      "競輪場名": "函館",
      "開催名": "能登半島支援・五稜郭杯争奪戦",
      "グレード": "G3",
      "レース番号": 6,
      "周長(m)": 400,
      "みなし直線(m)": 51.3,
      "カント角(度)": 30.6142,
      "レース種別": "Ｓ級二予選",
      "距離": 2025,
      "周回数": 5,
      "発走時刻": "17:15",
      "投票締切": "17:12",
      "天候": "曇",
      "風速": "3.0"
    },
    {
      "race_key": "20240517_函館_7R",
      "開催日": "20240517",
      "競輪場コード": "11",
      "競輪場名": "函館",
      "開催名": "能登半島支援・五稜郭杯争奪戦",
      "グレード": "G3",
      "レース番号": 7,
      "周長(m)": 400,
      "みなし直線(m)": 51.3,
      "カント角(度)": 30.6142,
      "レース種別": "Ｓ級二予選",
      "距離": 2025,
      "周回数": 5,
      "発走時刻": "17:45",
      "投票締切": "17:42",
      "天候": "曇",
      "風速": "2.0"
    },
    {
      "race_key": "20240517_函館_8R",
      "開催日": "20240517",
      "競輪場コード": "11",
      "競輪場名": "函館",
      "開催名": "能登半島支援・五稜郭杯争奪戦",
      "グレード": "G3",
      "レース番号": 8,
      "周長(m)": 400,
      "みなし直線(m)": 51.3,
      "カント角(度)": 30.6142,
      "レース種別": "Ｓ級二予選",
      "距離": 2025,
      "周回数": 5,
      "発走時刻": "18:15",
      "投票締切": "18:12",
      "天候": "曇",
      "風速": "2.0"
    },
    {
      "race_key": "20240517_函館_9R",
      "開催日": "20240517",
      "競輪場コード": "11",
      "競輪場名": "函館",
      "開催名": "能登半島支援・五稜郭杯争奪戦",
      "グレード": "G3",
      "レース番号": 9,
      "周長(m)": 400,
      "みなし直線(m)": 51.3,
      "カント角(度)": 30.6142,
      "レース種別": "Ｓ級二予選",
      "距離": 2025,
      "周回数": 5,
      "発走時刻": "18:45",
      "投票締切": "18:42",
      "天候": "曇",
      "風速": "2.0"
    },
    {
      "race_key": "20240517_函館_10R",
      "開催日": "20240517",
      "競輪場コード": "11",
      "競輪場名": "函館",
      "開催名": "能登半島支援・五稜郭杯争奪戦",
      "グレード": "G3",
      "レース番号": 10,
      "周長(m)": 400,
      "みなし直線(m)": 51.3,
      "カント角(度)": 30.6142,
      "レース種別": "Ｓ級二予選",
      "距離": 2025,
      "周回数": 5,
      "発走時刻": "19:16",
      "投票締切": "19:13",
      "天候": "曇",
      "風速": "1.0"
    },
    {
      "race_key": "20240517_函館_11R",
      "開催日": "20240517",
      "競輪場コード": "11",
      "競輪場名": "函館",
      "開催名": "能登半島支援・五稜郭杯争奪戦",
      "グレード": "G3",
      "レース番号": 11,
      "周長(m)": 400,
      "みなし直線(m)": 51.3,
      "カント角(度)": 30.6142,
      "レース種別": "Ｓ級二予選",
      "距離": 2025,
      "周回数": 5,
      "発走時刻": "19:47",
      "投票締切": "19:44",
      "天候": "曇",
      "風速": "2.0"
    },
    {
      "race_key": "20240517_函館_12R",
      "開催日": "20240517",
      "競輪場コード": "11",
      "競輪場名": "函館",
      "開催名": "能登半島支援・五稜郭杯争奪戦",
      "グレード": "G3",
      "レース番号": 12,
      "周長(m)": 400,
      "みなし直線(m)": 51.3,
      "カント角(度)": 30.6142,
      "レース種別": "Ｓ級二予選",
      "距離": 2025,
      "周回数": 5,
      "発走時刻": "20:20",
      "投票締切": "20:17",
      "天候": "曇",
      "風速": "2.0"
    },
    {
      "race_key": "20240517_和歌山_1R",
      "開催日": "20240517",
      "競輪場コード": "55",
      "競輪場名": "和歌山",
      "開催名": "オッズパークのオズパ祭２杯",
      "グレード": "F1",
      "レース番号": 1,
      "周長(m)": 400,
      "みなし直線(m)": 59.9,
      "カント角(度)": 32.2519,
      "レース種別": "Ａ級一般",
      "距離": 1625,
      "周回数": 4,
      "発走時刻": "10:40",
      "投票締切": "10:37",
      "天候": "晴",
      "風速": "2.2"
    },
    {
      "race_key": "20240517_和歌山_2R",
      "開催日": "20240517",
      "競輪場コード": "55",
      "競輪場名": "和歌山",
      "開催名": "オッズパークのオズパ祭２杯",
      "グレード": "F1",
      "レース番号": 2,
      "周長(m)": 400,
      "みなし直線(m)": 59.9,
      "カント角(度)": 32.2519,
      "レース種別": "Ａ級一般",
      "距離": 1625,
      "周回数": 4,
      "発走時刻": "11:05",
      "投票締切": "11:02",
      "天候": "晴",
      "風速": "1.8"
    },
    {
      "race_key": "20240517_和歌山_3R",
      "開催日": "20240517",
      "競輪場コード": "55",
      "競輪場名": "和歌山",
      "開催名": "オッズパークのオズパ祭２杯",
      "グレード": "F1",
      "レース番号": 3,
      "周長(m)": 400,
      "みなし直線(m)": 59.9,
      "カント角(度)": 32.2519,
      "レース種別": "Ａ級特選",
      "距離": 1625,
      "周回数": 4,
      "発走時刻": "11:30",
      "投票締切": "11:27",
      "天候": "晴",
      "風速": "1.3"
    },
    {
      "race_key": "20240517_和歌山_4R",
      "開催日": "20240517",
      "競輪場コード": "55",
      "競輪場名": "和歌山",
      "開催名": "オッズパークのオズパ祭２杯",
      "グレード": "F1",
      "レース番号": 4,
      "周長(m)": 400,
      "みなし直線(m)": 59.9,
      "カント角(度)": 32.2519,
      "レース種別": "Ａ級特選",
      "距離": 1625,
      "周回数": 4,
      "発走時刻": "12:00",
      "投票締切": "11:57",
      "天候": "晴",
      "風速": "1.3"
    },
    {
      "race_key": "20240517_和歌山_5R",
      "開催日": "20240517",
      "競輪場コード": "55",
      "競輪場名": "和歌山",
      "開催名": "オッズパークのオズパ祭２杯",
      "グレード": "F1",
      "レース番号": 5,
      "周長(m)": 400,
      "みなし直線(m)": 59.9,
      "カント角(度)": 32.2519,
      "レース種別": "Ｓ級一般",
      "距離": 2025,
      "周回数": 5,
      "発走時刻": "12:35",
      "投票締切": "12:32",
      "天候": "晴",
      "風速": "0.9"
    },
    {
      "race_key": "20240517_和歌山_6R",
      "開催日": "20240517",
      "競輪場コード": "55",
      "競輪場名": "和歌山",
      "開催名": "オッズパークのオズパ祭２杯",
      "グレード": "F1",
      "レース番号": 6,
      "周長(m)": 400,
      "みなし直線(m)": 59.9,
      "カント角(度)": 32.2519,
      "レース種別": "Ｓ級一般",
      "距離": 2025,
      "周回数": 5,
      "発走時刻": "13:05",
      "投票締切": "13:02",
      "天候": "晴",
      "風速": "2.2"
    },
    {
      "race_key": "20240517_和歌山_7R",
      "開催日": "20240517",
      "競輪場コード": "55",
      "競輪場名": "和歌山",
      "開催名": "オッズパークのオズパ祭２杯",
      "グレード": "F1",
      "レース番号": 7,
      "周長(m)": 400,
      "みなし直線(m)": 59.9,
      "カント角(度)": 32.2519,
      "レース種別": "Ｓ級一般",
      "距離": 2025,
      "周回数": 5,
      "発走時刻": "13:35",
      "投票締切": "13:32",
      "天候": "晴",
      "風速": "2.2"
    },
    {
      "race_key": "20240517_和歌山_8R",
      "開催日": "20240517",
      "競輪場コード": "55",
      "競輪場名": "和歌山",
      "開催名": "オッズパークのオズパ祭２杯",
      "グレード": "F1",
      "レース番号": 8,
      "周長(m)": 400,
      "みなし直線(m)": 59.9,
      "カント角(度)": 32.2519,
      "レース種別": "Ｓ級特選",
      "距離": 2025,
      "周回数": 5,
      "発走時刻": "14:05",
      "投票締切": "14:02",
      "天候": "晴",
      "風速": "2.7"
    },
    {
      "race_key": "20240517_和歌山_9R",
      "開催日": "20240517",
      "競輪場コード": "55",
      "競輪場名": "和歌山",
      "開催名": "オッズパークのオズパ祭２杯",
      "グレード": "F1",
      "レース番号": 9,
      "周長(m)": 400,
      "みなし直線(m)": 59.9,
      "カント角(度)": 32.2519,
      "レース種別": "Ｓ級特選",
      "距離": 2025,
      "周回数": 5,
      "発走時刻": "14:35",
      "投票締切": "14:32",
      "天候": "晴",
      "風速": "2.2"
    },
    {
      "race_key": "20240517_和歌山_10R",
      "開催日": "20240517",
      "競輪場コード": "55",
      "競輪場名": "和歌山",
      "開催名": "オッズパークのオズパ祭２杯",
      "グレード": "F1",
      "レース番号": 10,
      "周長(m)": 400,
      "みなし直線(m)": 59.9,
      "カント角(度)": 32.2519,
      "レース種別": "Ｓ級特選",
      "距離": 2025,
      "周回数": 5,
      "発走時刻": "15:05",
      "投票締切": "15:02",
      "天候": "晴",
      "風速": "2.7"
    },
    {
      "race_key": "20240517_和歌山_11R",
      "開催日": "20240517",
      "競輪場コード": "55",
      "競輪場名": "和歌山",
      "開催名": "オッズパークのオズパ祭２杯",
      "グレード": "F1",
      "レース番号": 11,
      "周長(m)": 400,
      "みなし直線(m)": 59.9,
      "カント角(度)": 32.2519,
      "レース種別": "Ａ級決勝",
      "距離": 1625,
      "周回数": 4,
      "発走時刻": "15:35",
      "投票締切": "15:32",
      "天候": "晴",
      "風速": "2.7"
    },
    {
      "race_key": "20240517_和歌山_12R",
      "開催日": "20240517",
      "競輪場コード": "55",
      "競輪場名": "和歌山",
      "開催名": "オッズパークのオズパ祭２杯",
      "グレード": "F1",
      "レース番号": 12,
      "周長(m)": 400,
      "みなし直線(m)": 59.9,
      "カント角(度)": 32.2519,
      "レース種別": "Ｓ級決勝",
      "距離": 2025,
      "周回数": 5,
      "発走時刻": "16:10",
      "投票締切": "16:07",
      "天候": "晴",
      "風速": "2.7"
    },
    {
      "race_key": "20240517_岐阜_1R",
      "開催日": "20240517",
      "競輪場コード": "43",
      "競輪場名": "岐阜",
      "開催名": "競輪アプリはウィンチケット杯",
      "グレード": "F2",
      "レース番号": 1,
      "周長(m)": 400,
      "みなし直線(m)": 59.3,
      "カント角(度)": 32.2519,
      "レース種別": "Ａ級チ予選",
      "距離": 1625,
      "周回数": 4,
      "発走時刻": "21:02",
      "投票締切": "20:59",
      "天候": "晴",
      "風速": "0.3"
    },
    {
      "race_key": "20240517_岐阜_2R",
      "開催日": "20240517",
      "競輪場コード": "43",
      "競輪場名": "岐阜",
      "開催名": "競輪アプリはウィンチケット杯",
      "グレード": "F2",
      "レース番号": 2,
      "周長(m)": 400,
      "みなし直線(m)": 59.3,
      "カント角(度)": 32.2519,
      "レース種別": "Ａ級チ予選",
      "距離": 1625,
      "周回数": 4,
      "発走時刻": "21:26",
      "投票締切": "21:23",
      "天候": "晴",
      "風速": "0.3"
    },
    {
      "race_key": "20240517_岐阜_3R",
      "開催日": "20240517",
      "競輪場コード": "43",
      "競輪場名": "岐阜",
      "開催名": "競輪アプリはウィンチケット杯",
      "グレード": "F2",
      "レース番号": 3,
      "周長(m)": 400,
      "みなし直線(m)": 59.3,
      "カント角(度)": 32.2519,
      "レース種別": "Ａ級チ予選",
      "距離": 1625,
      "周回数": 4,
      "発走時刻": "21:50",
      "投票締切": "21:47",
      "天候": "晴",
      "風速": "0.3"
    },
    {
      "race_key": "20240517_岐阜_4R",
      "開催日": "20240517",
      "競輪場コード": "43",
      "競輪場名": "岐阜",
      "開催名": "競輪アプリはウィンチケット杯",
      "グレード": "F2",
      "レース番号": 4,
      "周長(m)": 400,
      "みなし直線(m)": 59.3,
      "カント角(度)": 32.2519,
      "レース種別": "Ａ級チ予選",
      "距離": 1625,
      "周回数": 4,
      "発走時刻": "22:14",
      "投票締切": "22:11",
      "天候": "晴",
      "風速": "0.3"
    },
    {
      "race_key": "20240517_岐阜_5R",
      "開催日": "20240517",
      "競輪場コード": "43",
      "競輪場名": "岐阜",
      "開催名": "競輪アプリはウィンチケット杯",
      "グレード": "F2",
      "レース番号": 5,
      "周長(m)": 400,
      "みなし直線(m)": 59.3,
      "カント角(度)": 32.2519,
      "レース種別": "Ａ級チ予選",
      "距離": 1625,
      "周回数": 4,
      "発走時刻": "22:38",
      "投票締切": "22:35",
      "天候": "晴",
      "風速": "0.3"
    },
    {
      "race_key": "20240517_岐阜_6R",
      "開催日": "20240517",
      "競輪場コード": "43",
      "競輪場名": "岐阜",
      "開催名": "競輪アプリはウィンチケット杯",
      "グレード": "F2",
      "レース番号": 6,
      "周長(m)": 400,
      "みなし直線(m)": 59.3,
      "カント角(度)": 32.2519,
      "レース種別": "Ａ級チ予選",
      "距離": 1625,
      "周回数": 4,
      "発走時刻": "23:04",
      "投票締切": "23:01",
      "天候": "晴",
      "風速": "0.3"
    },
    {
      "race_key": "20240517_岐阜_7R",
      "開催日": "20240517",
      "競輪場コード": "43",
      "競輪場名": "岐阜",
      "開催名": "競輪アプリはウィンチケット杯",
      "グレード": "F2",
      "レース番号": 7,
      "周長(m)": 400,
      "みなし直線(m)": 59.3,
      "カント角(度)": 32.2519,
      "レース種別": "Ａ級チ予選",
      "距離": 1625,
      "周回数": 4,
      "発走時刻": "23:30",
      "投票締切": "23:27",
      "天候": "晴",
      "風速": "0.3"
    },
    {
      "race_key": "20240517_久留米_1R",
      "開催日": "20240517",
      "競輪場コード": "83",
      "競輪場名": "久留米",
      "開催名": "オッズパークのオズパ祭２杯",
      "グレード": "F2",
      "レース番号": 1,
      "周長(m)": 400,
      "みなし直線(m)": 50.7,
      "カント角(度)": 31.4769,
      "レース種別": "Ａ級チ予選",
      "距離": 1625,
      "周回数": 4,
      "発走時刻": "20:47",
      "投票締切": "20:44",
      "天候": "曇",
      "風速": "1.0"
    },
    {
      "race_key": "20240517_久留米_2R",
      "開催日": "20240517",
      "競輪場コード": "83",
      "競輪場名": "久留米",
      "開催名": "オッズパークのオズパ祭２杯",
      "グレード": "F2",
      "レース番号": 2,
      "周長(m)": 400,
      "みなし直線(m)": 50.7,
      "カント角(度)": 31.4769,
      "レース種別": "Ａ級チ予選",
      "距離": 1625,
      "周回数": 4,
      "発走時刻": "21:12",
      "投票締切": "21:09",
      "天候": "曇",
      "風速": "0.5"
    },
    {
      "race_key": "20240517_久留米_3R",
      "開催日": "20240517",
      "競輪場コード": "83",
      "競輪場名": "久留米",
      "開催名": "オッズパークのオズパ祭２杯",
      "グレード": "F2",
      "レース番号": 3,
      "周長(m)": 400,
      "みなし直線(m)": 50.7,
      "カント角(度)": 31.4769,
      "レース種別": "Ａ級チ予選",
      "距離": 1625,
      "周回数": 4,
      "発走時刻": "21:37",
      "投票締切": "21:34",
      "天候": "曇",
      "風速": "1.0"
    },
    {
      "race_key": "20240517_久留米_4R",
      "開催日": "20240517",
      "競輪場コード": "83",
      "競輪場名": "久留米",
      "開催名": "オッズパークのオズパ祭２杯",
      "グレード": "F2",
      "レース番号": 4,
      "周長(m)": 400,
      "みなし直線(m)": 50.7,
      "カント角(度)": 31.4769,
      "レース種別": "Ａ級チ予選",
      "距離": 1625,
      "周回数": 4,
      "発走時刻": "22:02",
      "投票締切": "21:59",
      "天候": "曇",
      "風速": "0.5"
    },
    {
      "race_key": "20240517_久留米_5R",
      "開催日": "20240517",
      "競輪場コード": "83",
      "競輪場名": "久留米",
      "開催名": "オッズパークのオズパ祭２杯",
      "グレード": "F2",
      "レース番号": 5,
      "周長(m)": 400,
      "みなし直線(m)": 50.7,
      "カント角(度)": 31.4769,
      "レース種別": "Ａ級チ予選",
      "距離": 1625,
      "周回数": 4,
      "発走時刻": "22:27",
      "投票締切": "22:24",
      "天候": "曇",
      "風速": "1.0"
    },
    {
      "race_key": "20240517_久留米_6R",
      "開催日": "20240517",
      "競輪場コード": "83",
      "競輪場名": "久留米",
      "開催名": "オッズパークのオズパ祭２杯",
      "グレード": "F2",
      "レース番号": 6,
      "周長(m)": 400,
      "みなし直線(m)": 50.7,
      "カント角(度)": 31.4769,
      "レース種別": "Ａ級チ予選",
      "距離": 1625,
      "周回数": 4,
      "発走時刻": "22:52",
      "投票締切": "22:49",
      "天候": "曇",
      "風速": "1.0"
    },
    {
      "race_key": "20240517_久留米_7R",
      "開催日": "20240517",
      "競輪場コード": "83",
      "競輪場名": "久留米",
      "開催名": "オッズパークのオズパ祭２杯",
      "グレード": "F2",
      "レース番号": 7,
      "周長(m)": 400,
      "みなし直線(m)": 50.7,
      "カント角(度)": 31.4769,
      "レース種別": "Ａ級チ予選",
      "距離": 1625,
      "周回数": 4,
      "発走時刻": "23:17",
      "投票締切": "23:14",
      "天候": "曇",
      "風速": "1.0"
    },
    {
      "race_key": "20240517_別府_1R",
      "開催日": "20240517",
      "競輪場コード": "86",
      "競輪場名": "別府",
      "開催名": "ニッカン・コム杯",
      "グレード": "F2",
      "レース番号": 1,
      "周長(m)": 400,
      "みなし直線(m)": 59.9,
      "カント角(度)": 33.69,
      "レース種別": "Ａ級チ一般",
      "距離": 1625,
      "周回数": 4,
      "発走時刻": "08:30",
      "投票締切": "08:27",
      "天候": "晴",
      "風速": "2.0"
    },
    {
      "race_key": "20240517_別府_2R",
      "開催日": "20240517",
      "競輪場コード": "86",
      "競輪場名": "別府",
      "開催名": "ニッカン・コム杯",
      "グレード": "F2",
      "レース番号": 2,
      "周長(m)": 400,
      "みなし直線(m)": 59.9,
      "カント角(度)": 33.69,
      "レース種別": "Ａ級チ一般",
      "距離": 1625,
      "周回数": 4,
      "発走時刻": "08:50",
      "投票締切": "08:47",
      "天候": "晴",
      "風速": "2.5"
    },
    {
      "race_key": "20240517_別府_3R",
      "開催日": "20240517",
      "競輪場コード": "86",
      "競輪場名": "別府",
      "開催名": "ニッカン・コム杯",
      "グレード": "F2",
      "レース番号": 3,
      "周長(m)": 400,
      "みなし直線(m)": 59.9,
      "カント角(度)": 33.69,
      "レース種別": "Ａ級チ準決",
      "距離": 1625,
      "周回数": 4,
      "発走時刻": "09:10",
      "投票締切": "09:07",
      "天候": "晴",
      "風速": "2.5"
    },
    {
      "race_key": "20240517_別府_4R",
      "開催日": "20240517",
      "競輪場コード": "86",
      "競輪場名": "別府",
      "開催名": "ニッカン・コム杯",
      "グレード": "F2",
      "レース番号": 4,
      "周長(m)": 400,
      "みなし直線(m)": 59.9,
      "カント角(度)": 33.69,
      "レース種別": "Ａ級チ準決",
      "距離": 1625,
      "周回数": 4,
      "発走時刻": "09:30",
      "投票締切": "09:27",
      "天候": "晴",
      "風速": "1.5"
    },
    {
      "race_key": "20240517_別府_5R",
      "開催日": "20240517",
      "競輪場コード": "86",
      "競輪場名": "別府",
      "開催名": "ニッカン・コム杯",
      "グレード": "F2",
      "レース番号": 5,
      "周長(m)": 400,
      "みなし直線(m)": 59.9,
      "カント角(度)": 33.69,
      "レース種別": "Ａ級チ準決",
      "距離": 1625,
      "周回数": 4,
      "発走時刻": "09:50",
      "投票締切": "09:47",
      "天候": "晴",
      "風速": "1.5"
    },
    {
      "race_key": "20240517_別府_6R",
      "開催日": "20240517",
      "競輪場コード": "86",
      "競輪場名": "別府",
      "開催名": "ニッカン・コム杯",
      "グレード": "F2",
      "レース番号": 6,
      "周長(m)": 400,
      "みなし直線(m)": 59.9,
      "カント角(度)": 33.69,
      "レース種別": "Ｌ級ガ予２",
      "距離": 1625,
      "周回数": 4,
      "発走時刻": "10:10",
      "投票締切": "10:07",
      "天候": "晴",
      "風速": "1.5"
    },
    {
      "race_key": "20240517_別府_7R",
      "開催日": "20240517",
      "競輪場コード": "86",
      "競輪場名": "別府",
      "開催名": "ニッカン・コム杯",
      "グレード": "F2",
      "レース番号": 7,
      "周長(m)": 400,
      "みなし直線(m)": 59.9,
      "カント角(度)": 33.69,
      "レース種別": "Ｌ級ガ予２",
      "距離": 1625,
      "周回数": 4,
      "発走時刻": "10:30",
      "投票締切": "10:27",
      "天候": "晴",
      "風速": "1.5"
    }
  ]
}