{
  "target_date": "20240719",
  "race_count": 76,
  "races": [
    {
      "race_key": "20240719_平塚_1R",
      "開催日": "20240719",
      "競輪場コード": "35",
      "競輪場名": "平塚",
      "開催名": "篠崎愛イメキャラ就任記念ＯＰ杯",
      "グレード": "F1",
      "レース番号": 1,
      "周長(m)": 400,
      "みなし直線(m)": 54.2,
      "カント角(度)": 31.4769,
      "レース種別": "Ａ級予選",
      "距離": 1625,
      "周回数": 4,
      "発走時刻": "15:25",
      "投票締切": "15:22",
      "天候": "晴",
      "風速": "2.0"
    },
    {
      "race_key": "20240719_平塚_2R",
      "開催日": "20240719",
      "競輪場コード": "35",
      "競輪場名": "平塚",
      "開催名": "篠崎愛イメキャラ就任記念ＯＰ杯",
      "グレード": "F1",
      "レース番号": 2,
      "周長(m)": 400,
      "みなし直線(m)": 54.2,
      "カント角(度)": 31.4769,
      "レース種別": "Ａ級予選",
      "距離": 1625,
      "周回数": 4,
      "発走時刻": "15:50",
      "投票締切": "15:47",
      "天候": "晴",
      "風速": "2.0"
    },
    {
      "race_key": "20240719_平塚_3R",
      "開催日": "20240719",
      "競輪場コード": "35",
      "競輪場名": "平塚",
      "開催名": "篠崎愛イメキャラ就任記念ＯＰ杯",
      "グレード": "F1",
      "レース番号": 3,
      "周長(m)": 400,
      "みなし直線(m)": 54.2,
      "カント角(度)": 31.4769,
      "レース種別": "Ａ級予選",
      "距離": 1625,
      "周回数": 4,
      "発走時刻": "16:15",
      "投票締切": "16:12",
      "天候": "曇",
      "風速": "2.0"
    },
    {
      "race_key": "20240719_平塚_4R",
      "開催日": "20240719",
      "競輪場コード": "35",
      "競輪場名": "平塚",
      "開催名": "篠崎愛イメキャラ就任記念ＯＰ杯",
      "グレード": "F1",
      "レース番号": 4,
      "周長(m)": 400,
      "みなし直線(m)": 54.2,
      "カント角(度)": 31.4769,
      "レース種別": "Ａ級予選",
      "距離": 1625,
      "周回数": 4,
      "発走時刻": "16:40",
      "投票締切": "16:37",
      "天候": "曇",
      "風速": "2.0"
    },
    {
      "race_key": "20240719_平塚_5R",
      "開催日": "20240719",
      "競輪場コード": "35",
      "競輪場名": "平塚",
      "開催名": "篠崎愛イメキャラ就任記念ＯＰ杯",
      "グレード": "F1",
      "レース番号": 5,
      "周長(m)": 400,
      "みなし直線(m)": 54.2,
      "カント角(度)": 31.4769,
      "レース種別": "Ａ級初特選",
      "距離": 1625,
      "周回数": 4,
      "発走時刻": "17:06",
      "投票締切": "17:03",
      "天候": "曇",
      "風速": "2.0"
    },
    {
      "race_key": "20240719_平塚_6R",
      "開催日": "20240719",
      "競輪場コード": "35",
      "競輪場名": "平塚",
      "開催名": "篠崎愛イメキャラ就任記念ＯＰ杯",
      "グレード": "F1",
      "レース番号": 6,
      "周長(m)": 400,
      "みなし直線(m)": 54.2,
      "カント角(度)": 31.4769,
      "レース種別": "Ｌ級ガ予１",
      "距離": 1625,
      "周回数": 4,
      "発走時刻": "17:32",
      "投票締切": "17:29",
      "天候": "曇",
      "風速": "2.0"
    },
    {
      "race_key": "20240719_平塚_7R",
      "開催日": "20240719",
      "競輪場コード": "35",
      "競輪場名": "平塚",
      "開催名": "篠崎愛イメキャラ就任記念ＯＰ杯",
      "グレード": "F1",
      "レース番号": 7,
      "周長(m)": 400,
      "みなし直線(m)": 54.2,
      "カント角(度)": 31.4769,
      "レース種別": "Ｌ級ガ予１",
      "距離": 1625,
      "周回数": 4,
      "発走時刻": "17:58",
      "投票締切": "17:55",
      "天候": "曇",
      "風速": "2.0"
    },
    {
      "race_key": "20240719_平塚_8R",
      "開催日": "20240719",
      "競輪場コード": "35",
      "競輪場名": "平塚",
      "開催名": "篠崎愛イメキャラ就任記念ＯＰ杯",
      "グレード": "F1",
      "レース番号": 8,
      "周長(m)": 400,
      "みなし直線(m)": 54.2,
      "カント角(度)": 31.4769,
      "レース種別": "Ｓ級予選",
      "距離": 2025,
      "周回数": 5,
      "発走時刻": "18:26",
      "投票締切": "18:23",
      "天候": "曇",
      "風速": "2.0"
    },
    {
      "race_key": "20240719_平塚_9R",
      "開催日": "20240719",
      "競輪場コード": "35",
      "競輪場名": "平塚",
      "開催名": "篠崎愛イメキャラ就任記念ＯＰ杯",
      "グレード": "F1",
      "レース番号": 9,
      "周長(m)": 400,
      "みなし直線(m)": 54.2,
      "カント角(度)": 31.4769,
      "レース種別": "Ｓ級予選",
      "距離": 2025,
      "周回数": 5,
      "発走時刻": "18:54",
      "投票締切": "18:51",
      "天候": "曇",
      "風速": "1.5"
    },
    {
      "race_key": "20240719_平塚_10R",
      "開催日": "20240719",
      "競輪場コード": "35",
      "競輪場名": "平塚",
      "開催名": "篠崎愛イメキャラ就任記念ＯＰ杯",
      "グレード": "F1",
      "レース番号": 10,
      "周長(m)": 400,
      "みなし直線(m)": 54.2,
      "カント角(度)": 31.4769,
      "レース種別": "Ｓ級予選",
      "距離": 2025,
      "周回数": 5,
      "発走時刻": "19:24",
      "投票締切": "19:21",
      "天候": "曇",
      "風速": "1.5"
    },
    {
      "race_key": "20240719_平塚_11R",
      "開催日": "20240719",
      "競輪場コード": "35",
      "競輪場名": "平塚",
      "開催名": "篠崎愛イメキャラ就任記念ＯＰ杯",
      "グレード": "F1",
      "レース番号": 11,
      "周長(m)": 400,
      "みなし直線(m)": 54.2,
      "カント角(度)": 31.4769,
      "レース種別": "Ｓ級予選",
      "距離": 2025,
      "周回数": 5,
      "発走時刻": "19:54",
      "投票締切": "19:51",
      "天候": "曇",
      "風速": "1.5"
    },
    {
      "race_key": "20240719_平塚_12R",
      "開催日": "20240719",
      "競輪場コード": "35",
      "競輪場名": "平塚",
      "開催名": "篠崎愛イメキャラ就任記念ＯＰ杯",
      "グレード": "F1",
      "レース番号": 12,
      "周長(m)": 400,
      "みなし直線(m)": 54.2,
      "カント角(度)": 31.4769,
      "レース種別": "Ｓ級初特選",
      "距離": 2025,
      "周回数": 5,
      "発走時刻": "20:25",
      "投票締切": "20:22",
      "天候": "曇",
      "風速": "1.5"
    },
    {
      "race_key": "20240719_岐阜_1R",
      "開催日": "20240719",
      "競輪場コード": "43",
      "競輪場名": "岐阜",
      "開催名": "スポーツ報知杯・ＨＰＣＪＣ杯",
      "グレード": "F1",
      "レース番号": 1,
      "周長(m)": 400,
      "みなし直線(m)": 59.3,
      "カント角(度)": 32.2519,
      "レース種別": "Ａ級一般",
      "距離": 1625,
      "周回数": 4,
      "発走時刻": "10:31",
      "投票締切": "10:28",
      "天候": "曇",
      "風速": "0.5"
    },
    {
      "race_key": "20240719_岐阜_2R",
      "開催日": "20240719",
      "競輪場コード": "43",
      "競輪場名": "岐阜",
      "開催名": "スポーツ報知杯・ＨＰＣＪＣ杯",
      "グレード": "F1",
      "レース番号": 2,
      "周長(m)": 400,
      "みなし直線(m)": 59.3,
      "カント角(度)": 32.2519,
      "レース種別": "Ａ級一般",
      "距離": 1625,
      "周回数": 4,
      "発走時刻": "10:59",
      "投票締切": "10:56",
      "天候": "曇",
      "風速": "1.0"
    },
    {
      "race_key": "20240719_岐阜_3R",
      "開催日": "20240719",
      "競輪場コード": "43",
      "競輪場名": "岐阜",
      "開催名": "スポーツ報知杯・ＨＰＣＪＣ杯",
      "グレード": "F1",
      "レース番号": 3,
      "周長(m)": 400,
      "みなし直線(m)": 59.3,
      "カント角(度)": 32.2519,
      "レース種別": "Ａ級特選",
      "距離": 1625,
      "周回数": 4,
      "発走時刻": "11:27",
      "投票締切": "11:24",
      "天候": "曇",
      "風速": "1.0"
    },
    {
      "race_key": "20240719_岐阜_4R",
      "開催日": "20240719",
      "競輪場コード": "43",
      "競輪場名": "岐阜",
      "開催名": "スポーツ報知杯・ＨＰＣＪＣ杯",
      "グレード": "F1",
      "レース番号": 4,
      "周長(m)": 400,
      "みなし直線(m)": 59.3,
      "カント角(度)": 32.2519,
      "レース種別": "Ａ級特選",
      "距離": 1625,
      "周回数": 4,
      "発走時刻": "11:57",
      "投票締切": "11:54",
      "天候": "曇",
      "風速": "1.0"
    },
    {
      "race_key": "20240719_岐阜_5R",
      "開催日": "20240719",
      "競輪場コード": "43",
      "競輪場名": "岐阜",
      "開催名": "スポーツ報知杯・ＨＰＣＪＣ杯",
      "グレード": "F1",
      "レース番号": 5,
      "周長(m)": 400,
      "みなし直線(m)": 59.3,
      "カント角(度)": 32.2519,
      "レース種別": "Ｓ級一般",
      "距離": 2025,
      "周回数": 5,
      "発走時刻": "12:27",
      "投票締切": "12:24",
      "天候": "曇",
      "風速": "0.5"
    },
    {
      "race_key": "20240719_岐阜_6R",
      "開催日": "20240719",
      "競輪場コード": "43",
      "競輪場名": "岐阜",
      "開催名": "スポーツ報知杯・ＨＰＣＪＣ杯",
      "グレード": "F1",
      "レース番号": 6,
      "周長(m)": 400,
      "みなし直線(m)": 59.3,
      "カント角(度)": 32.2519,
      "レース種別": "Ｓ級一般",
      "距離": 2025,
      "周回数": 5,
      "発走時刻": "12:58",
      "投票締切": "12:55",
      "天候": "曇",
      "風速": "0.5"
    },
    {
      "race_key": "20240719_岐阜_7R",
      "開催日": "20240719",
      "競輪場コード": "43",
      "競輪場名": "岐阜",
      "開催名": "スポーツ報知杯・ＨＰＣＪＣ杯",
      "グレード": "F1",
      "レース番号": 7,
      "周長(m)": 400,
      "みなし直線(m)": 59.3,
      "カント角(度)": 32.2519,
      "レース種別": "Ｓ級一般",
      "距離": 2025,
      "周回数": 5,
      "発走時刻": "13:29",
      "投票締切": "13:26",
      "天候": "曇",
      "風速": "0.5"
    },
    {
      "race_key": "20240719_岐阜_8R",
      "開催日": "20240719",
      "競輪場コード": "43",
      "競輪場名": "岐阜",
      "開催名": "スポーツ報知杯・ＨＰＣＪＣ杯",
      "グレード": "F1",
      "レース番号": 8,
      "周長(m)": 400,
      "みなし直線(m)": 59.3,
      "カント角(度)": 32.2519,
      "レース種別": "Ｓ級特選",
      "距離": 2025,
      "周回数": 5,
      "発走時刻": "14:01",
      "投票締切": "13:58",
      "天候": "曇",
      "風速": "0.5"
    },
    {
      "race_key": "20240719_岐阜_9R",
      "開催日": "20240719",
      "競輪場コード": "43",
      "競輪場名": "岐阜",
      "開催名": "スポーツ報知杯・ＨＰＣＪＣ杯",
      "グレード": "F1",
      "レース番号": 9,
      "周長(m)": 400,
      "みなし直線(m)": 59.3,
      "カント角(度)": 32.2519,
      "レース種別": "Ｓ級特選",
      "距離": 2025,
      "周回数": 5,
      "発走時刻": "14:33",
      "投票締切": "14:30",
      "天候": "曇",
      "風速": "0.5"
    },
    {
      "race_key": "20240719_岐阜_10R",
      "開催日": "20240719",
      "競輪場コード": "43",
      "競輪場名": "岐阜",
      "開催名": "スポーツ報知杯・ＨＰＣＪＣ杯",
      "グレード": "F1",
      "レース番号": 10,
      "周長(m)": 400,
      "みなし直線(m)": 59.3,
      "カント角(度)": 32.2519,
      "レース種別": "Ｓ級特選",
      "距離": 2025,
      "周回数": 5,
      "発走時刻": "15:05",
      "投票締切": "15:02",
      "天候": "曇",
      "風速": "0.5"
    },
    {
      "race_key": "20240719_岐阜_11R",
      "開催日": "20240719",
      "競輪場コード": "43",
      "競輪場名": "岐阜",
      "開催名": "スポーツ報知杯・ＨＰＣＪＣ杯",
      "グレード": "F1",
      "レース番号": 11,
      "周長(m)": 400,
      "みなし直線(m)": 59.3,
      "カント角(度)": 32.2519,
      "レース種別": "Ａ級決勝",
      "距離": 1625,
      "周回数": 4,
      "発走時刻": "15:38",
      "投票締切": "15:35",
      "天候": "晴",
      "風速": "0.5"
    },
    {
      "race_key": "20240719_岐阜_12R",
      "開催日": "20240719",
      "競輪場コード": "43",
      "競輪場名": "岐阜",
      "開催名": "スポーツ報知杯・ＨＰＣＪＣ杯",
      "グレード": "F1",
      "レース番号": 12,
      "周長(m)": 400,
      "みなし直線(m)": 59.3,
      "カント角(度)": 32.2519,
      "レース種別": "Ｓ級決勝",
      "距離": 2025,
      "周回数": 5,
      "発走時刻": "16:11",
      "投票締切": "16:08",
      "天候": "曇",
      "風速": "0.5"
    },
    {
      "race_key": "20240719_宇都宮_1R",
      "開催日": "20240719",
      "競輪場コード": "24",
      "競輪場名": "宇都宮",
      "開催名": "ＷＩＮＴＩＣＫＥＴ杯",
      "グレード": "F2",
      "レース番号": 1,
      "周長(m)": 500,
      "みなし直線(m)": 63.3,
      "カント角(度)": 25.7956,
      "レース種別": "Ａ級チ予選",
      "距離": 1525,
      "周回数": 3,
      "発走時刻": "21:02",
      "投票締切": "20:59",
      "天候": "曇",
      "風速": "0.0"
    },
    {
      "race_key": "20240719_宇都宮_2R",
      "開催日": "20240719",
      "競輪場コード": "24",
      "競輪場名": "宇都宮",
      "開催名": "ＷＩＮＴＩＣＫＥＴ杯",
      "グレード": "F2",
      "レース番号": 2,
      "周長(m)": 500,
      "みなし直線(m)": 63.3,
      "カント角(度)": 25.7956,
      "レース種別": "Ａ級チ予選",
      "距離": 1525,
      "周回数": 3,
      "発走時刻": "21:26",
      "投票締切": "21:23",
      "天候": "曇",
      "風速": "0.0"
    },
    {
      "race_key": "20240719_宇都宮_3R",
      "開催日": "20240719",
      "競輪場コード": "24",
      "競輪場名": "宇都宮",
      "開催名": "ＷＩＮＴＩＣＫＥＴ杯",
      "グレード": "F2",
      "レース番号": 3,
      "周長(m)": 500,
      "みなし直線(m)": 63.3,
      "カント角(度)": 25.7956,
      "レース種別": "Ａ級チ予選",
      "距離": 1525,
      "周回数": 3,
      "発走時刻": "21:50",
      "投票締切": "21:47",
      "天候": "曇",
      "風速": "0.0"
    },
    {
      "race_key": "20240719_宇都宮_4R",
      "開催日": "20240719",
      "競輪場コード": "24",
      "競輪場名": "宇都宮",
      "開催名": "ＷＩＮＴＩＣＫＥＴ杯",
      "グレード": "F2",
      "レース番号": 4,
      "周長(m)": 500,
      "みなし直線(m)": 63.3,
      "カント角(度)": 25.7956,
      "レース種別": "Ａ級チ予選",
      "距離": 1525,
      "周回数": 3,
      "発走時刻": "22:14",
      "投票締切": "22:11",
      "天候": "曇",
      "風速": "0.0"
    },
    {
      "race_key": "20240719_宇都宮_5R",
      "開催日": "20240719",
      "競輪場コード": "24",
      "競輪場名": "宇都宮",
      "開催名": "ＷＩＮＴＩＣＫＥＴ杯",
      "グレード": "F2",
      "レース番号": 5,
      "周長(m)": 500,
      "みなし直線(m)": 63.3,
      "カント角(度)": 25.7956,
      "レース種別": "Ａ級チ予選",
      "距離": 1525,
      "周回数": 3,
      "発走時刻": "22:38",
      "投票締切": "22:35",
      "天候": "曇",
      "風速": "0.0"
    },
    {
      "race_key": "20240719_宇都宮_6R",
      "開催日": "20240719",
      "競輪場コード": "24",
      "競輪場名": "宇都宮",
      "開催名": "ＷＩＮＴＩＣＫＥＴ杯",
      "グレード": "F2",
      "レース番号": 6,
      "周長(m)": 500,
      "みなし直線(m)": 63.3,
      "カント角(度)": 25.7956,
      "レース種別": "Ａ級チ予選",
      "距離": 1525,
      "周回数": 3,
      "発走時刻": "23:04",
      "投票締切": "23:01",
      "天候": "晴",
      "風速": "0.0"
    },
    {
      "race_key": "20240719_宇都宮_7R",
      "開催日": "20240719",
      "競輪場コード": "24",
      "競輪場名": "宇都宮",
      "開催名": "ＷＩＮＴＩＣＫＥＴ杯",
      "グレード": "F2",
      "レース番号": 7,
      "周長(m)": 500,
      "みなし直線(m)": 63.3,
      "カント角(度)": 25.7956,
      "レース種別": "Ａ級チ予選",
      "距離": 1525,
      "周回数": 3,
      "発走時刻": "23:30",
      "投票締切": "23:27",
      "天候": "晴",
      "風速": "0.0"
    },
    {
      "race_key": "20240719_大宮_1R",
      "開催日": "20240719",
      "競輪場コード": "25",
      "競輪場名": "大宮",
      "開催名": "競輪公式投票ＣＴＣ杯",
      "グレード": "F2",
      "レース番号": 1,
      "周長(m)": 500,
      "みなし直線(m)": 66.7,
      "カント角(度)": 26.2778,
      "レース種別": "Ａ級チ予選",
      "距離": 1525,
      "周回数": 3,
      "発走時刻": "08:40",
      "投票締切": "08:37",
      "天候": "曇",
      "風速": "1.0"
    },
    {
      "race_key": "20240719_大宮_2R",
      "開催日": "20240719",
      "競輪場コード": "25",
      "競輪場名": "大宮",
      "開催名": "競輪公式投票ＣＴＣ杯",
      "グレード": "F2",
      "レース番号": 2,
      "周長(m)": 500,
      "みなし直線(m)": 66.7,
      "カント角(度)": 26.2778,
      "レース種別": "Ａ級チ予選",
      "距離": 1525,
      "周回数": 3,
      "発走時刻": "09:00",
      "投票締切": "08:57",
      "天候": "曇",
      "風速": "1.0"
    },
    {
      "race_key": "20240719_大宮_3R",
      "開催日": "20240719",
      "競輪場コード": "25",
      "競輪場名": "大宮",
      "開催名": "競輪公式投票ＣＴＣ杯",
      "グレード": "F2",
      "レース番号": 3,
      "周長(m)": 500,
      "みなし直線(m)": 66.7,
      "カント角(度)": 26.2778,
      "レース種別": "Ａ級チ予選",
      "距離": 1525,
      "周回数": 3,
      "発走時刻": "09:20",
      "投票締切": "09:17",
      "天候": "曇",
      "風速": "1.0"
    },
    {
      "race_key": "20240719_大宮_4R",
      "開催日": "20240719",
      "競輪場コード": "25",
      "競輪場名": "大宮",
      "開催名": "競輪公式投票ＣＴＣ杯",
      "グレード": "F2",
      "レース番号": 4,
      "周長(m)": 500,
      "みなし直線(m)": 66.7,
      "カント角(度)": 26.2778,
      "レース種別": "Ａ級チ予選",
      "距離": 1525,
      "周回数": 3,
      "発走時刻": "09:40",
      "投票締切": "09:37",
      "天候": "曇",
      "風速": "1.0"
    },
    {
      "race_key": "20240719_大宮_5R",
      "開催日": "20240719",
      "競輪場コード": "25",
      "競輪場名": "大宮",
      "開催名": "競輪公式投票ＣＴＣ杯",
      "グレード": "F2",
      "レース番号": 5,
      "周長(m)": 500,
      "みなし直線(m)": 66.7,
      "カント角(度)": 26.2778,
      "レース種別": "Ａ級チ予選",
      "距離": 1525,
      "周回数": 3,
      "発走時刻": "10:00",
      "投票締切": "09:57",
      "天候": "曇",
      "風速": "1.0"
    },
    {
      "race_key": "20240719_大宮_6R",
      "開催日": "20240719",
      "競輪場コード": "25",
      "競輪場名": "大宮",
      "開催名": "競輪公式投票ＣＴＣ杯",
      "グレード": "F2",
      "レース番号": 6,
      "周長(m)": 500,
      "みなし直線(m)": 66.7,
      "カント角(度)": 26.2778,
      "レース種別": "Ａ級チ予選",
      "距離": 1525,
      "周回数": 3,
      "発走時刻": "10:20",
      "投票締切": "10:17",
      "天候": "曇",
      "風速": "1.0"
    },
    {
      "race_key": "20240719_大宮_7R",
      "開催日": "20240719",
      "競輪場コード": "25",
      "競輪場名": "大宮",
      "開催名": "競輪公式投票ＣＴＣ杯",
      "グレード": "F2",
      "レース番号": 7,
      "周長(m)": 500,
      "みなし直線(m)": 66.7,
      "カント角(度)": 26.2778,
      "レース種別": "Ａ級チ予選",
      "距離": 1525,
      "周回数": 3,
      "発走時刻": "10:40",
      "投票締切": "10:37",
      "天候": "曇",
      "風速": "1.0"
    },
    {
      "race_key": "20240719_大垣_1R",
      "開催日": "20240719",
      "競輪場コード": "44",
      "競輪場名": "大垣",
      "開催名": "Ｋドリームス杯サテライト姫路賞",
      "グレード": "F2",
      "レース番号": 1,
      "周長(m)": 400,
      "みなし直線(m)": 56,
      "カント角(度)": 30.6189,
      "レース種別": "Ａ級予選",
      "距離": 1625,
      "周回数": 4,
      "発走時刻": "20:50",
      "投票締切": "20:47",
      "天候": "曇",
      "風速": "0.5"
    },
    {
      "race_key": "20240719_大垣_2R",
      "開催日": "20240719",
      "競輪場コード": "44",
      "競輪場名": "大垣",
      "開催名": "Ｋドリームス杯サテライト姫路賞",
      "グレード": "F2",
      "レース番号": 2,
      "周長(m)": 400,
      "みなし直線(m)": 56,
      "カント角(度)": 30.6189,
      "レース種別": "Ａ級予選",
      "距離": 1625,
      "周回数": 4,
      "発走時刻": "21:14",
      "投票締切": "21:11",
      "天候": "曇",
      "風速": "0.3"
    },
    {
      "race_key": "20240719_大垣_3R",
      "開催日": "20240719",
      "競輪場コード": "44",
      "競輪場名": "大垣",
      "開催名": "Ｋドリームス杯サテライト姫路賞",
      "グレード": "F2",
      "レース番号": 3,
      "周長(m)": 400,
      "みなし直線(m)": 56,
      "カント角(度)": 30.6189,
      "レース種別": "Ａ級予選",
      "距離": 1625,
      "周回数": 4,
      "発走時刻": "21:38",
      "投票締切": "21:35",
      "天候": "曇",
      "風速": "0.1"
    },
    {
      "race_key": "20240719_大垣_4R",
      "開催日": "20240719",
      "競輪場コード": "44",
      "競輪場名": "大垣",
      "開催名": "Ｋドリームス杯サテライト姫路賞",
      "グレード": "F2",
      "レース番号": 4,
      "周長(m)": 400,
      "みなし直線(m)": 56,
      "カント角(度)": 30.6189,
      "レース種別": "Ａ級予選",
      "距離": 1625,
      "周回数": 4,
      "発走時刻": "22:02",
      "投票締切": "21:59",
      "天候": "曇",
      "風速": "0.3"
    },
    {
      "race_key": "20240719_大垣_5R",
      "開催日": "20240719",
      "競輪場コード": "44",
      "競輪場名": "大垣",
      "開催名": "Ｋドリームス杯サテライト姫路賞",
      "グレード": "F2",
      "レース番号": 5,
      "周長(m)": 400,
      "みなし直線(m)": 56,
      "カント角(度)": 30.6189,
      "レース種別": "Ａ級予選",
      "距離": 1625,
      "周回数": 4,
      "発走時刻": "22:26",
      "投票締切": "22:23",
      "天候": "曇",
      "風速": "0.5"
    },
    {
      "race_key": "20240719_大垣_6R",
      "開催日": "20240719",
      "競輪場コード": "44",
      "競輪場名": "大垣",
      "開催名": "Ｋドリームス杯サテライト姫路賞",
      "グレード": "F2",
      "レース番号": 6,
      "周長(m)": 400,
      "みなし直線(m)": 56,
      "カント角(度)": 30.6189,
      "レース種別": "Ａ級予選",
      "距離": 1625,
      "周回数": 4,
      "発走時刻": "22:52",
      "投票締切": "22:49",
      "天候": "曇",
      "風速": "0.2"
    },
    {
      "race_key": "20240719_大垣_7R",
      "開催日": "20240719",
      "競輪場コード": "44",
      "競輪場名": "大垣",
      "開催名": "Ｋドリームス杯サテライト姫路賞",
      "グレード": "F2",
      "レース番号": 7,
      "周長(m)": 400,
      "みなし直線(m)": 56,
      "カント角(度)": 30.6189,
      "レース種別": "Ａ級初特選",
      "距離": 1625,
      "周回数": 4,
      "発走時刻": "23:18",
      "投票締切": "23:15",
      "天候": "曇",
      "風速": "0.3"
    },
    {
      "race_key": "20240719_向日町_1R",
      "開催日": "20240719",
      "競輪場コード": "54",
      "競輪場名": "向日町",
      "開催名": "みんなの競輪カップ　京蓮の花賞",
      "グレード": "F2",
      "レース番号": 1,
      "周長(m)": 400,
      "みなし直線(m)": 47.3,
      "カント角(度)": 30.4853,
      "レース種別": "Ａ級チ一般",
      "距離": 1625,
      "周回数": 4,
      "発走時刻": "10:50",
      "投票締切": "10:47",
      "天候": "晴",
      "風速": "1.8"
    },
    {
      "race_key": "20240719_向日町_2R",
      "開催日": "20240719",
      "競輪場コード": "54",
      "競輪場名": "向日町",
      "開催名": "みんなの競輪カップ　京蓮の花賞",
      "グレード": "F2",
      "レース番号": 2,
      "周長(m)": 400,
      "みなし直線(m)": 47.3,
      "カント角(度)": 30.4853,
      "レース種別": "Ａ級チ一般",
      "距離": 1625,
      "周回数": 4,
      "発走時刻": "11:18",
      "投票締切": "11:15",
      "天候": "晴",
      "風速": "2.2"
    },
    {
      "race_key": "20240719_向日町_3R",
      "開催日": "20240719",
      "競輪場コード": "54",
      "競輪場名": "向日町",
      "開催名": "みんなの競輪カップ　京蓮の花賞",
      "グレード": "F2",
      "レース番号": 3,
      "周長(m)": 400,
      "みなし直線(m)": 47.3,
      "カント角(度)": 30.4853,
      "レース種別": "Ａ級チ選抜",
      "距離": 1625,
      "周回数": 4,
      "発走時刻": "11:46",
      "投票締切": "11:43",
      "天候": "晴",
      "風速": "2.7"
    },
    {
      "race_key": "20240719_向日町_4R",
      "開催日": "20240719",
      "競輪場コード": "54",
      "競輪場名": "向日町",
      "開催名": "みんなの競輪カップ　京蓮の花賞",
      "グレード": "F2",
      "レース番号": 4,
      "周長(m)": 400,
      "みなし直線(m)": 47.3,
      "カント角(度)": 30.4853,
      "レース種別": "Ａ級チ選抜",
      "距離": 1625,
      "周回数": 4,
      "発走時刻": "12:16",
      "投票締切": "12:13",
      "天候": "晴",
      "風速": "2.7"
    },
    {
      "race_key": "20240719_向日町_5R",
      "開催日": "20240719",
      "競輪場コード": "54",
      "競輪場名": "向日町",
      "開催名": "みんなの競輪カップ　京蓮の花賞",
      "グレード": "F2",
      "レース番号": 5,
      "周長(m)": 400,
      "みなし直線(m)": 47.3,
      "カント角(度)": 30.4853,
      "レース種別": "Ａ級一般",
      "距離": 1625,
      "周回数": 4,
      "発走時刻": "12:46",
      "投票締切": "12:43",
      "天候": "晴",
      "風速": "2.7"
    },
    {
      "race_key": "20240719_向日町_6R",
      "開催日": "20240719",
      "競輪場コード": "54",
      "競輪場名": "向日町",
      "開催名": "みんなの競輪カップ　京蓮の花賞",
      "グレード": "F2",
      "レース番号": 6,
      "周長(m)": 400,
      "みなし直線(m)": 47.3,
      "カント角(度)": 30.4853,
      "レース種別": "Ａ級一般",
      "距離": 1625,
      "周回数": 4,
      "発走時刻": "13:17",
      "投票締切": "13:14",
      "天候": "晴",
      "風速": "2.7"
    },
    {
      "race_key": "20240719_向日町_7R",
      "開催日": "20240719",
      "競輪場コード": "54",
      "競輪場名": "向日町",
      "開催名": "みんなの競輪カップ　京蓮の花賞",
      "グレード": "F2",
      "レース番号": 7,
      "周長(m)": 400,
      "みなし直線(m)": 47.3,
      "カント角(度)": 30.4853,
      "レース種別": "Ａ級一般",
      "距離": 1625,
      "周回数": 4,
      "発走時刻": "13:48",
      "投票締切": "13:45",
      "天候": "晴",
      "風速": "2.7"
    },
    {
      "race_key": "20240719_向日町_8R",
      "開催日": "20240719",
      "競輪場コード": "54",
      "競輪場名": "向日町",
      "開催名": "みんなの競輪カップ　京蓮の花賞",
      "グレード": "F2",
      "レース番号": 8,
      "周長(m)": 400,
      "みなし直線(m)": 47.3,
      "カント角(度)": 30.4853,
      "レース種別": "Ａ級特選",
      "距離": 1625,
      "周回数": 4,
      "発走時刻": "14:20",
      "投票締切": "14:17",
      "天候": "晴",
      "風速": "2.2"
    },
    {
      "race_key": "20240719_向日町_9R",
      "開催日": "20240719",
      "競輪場コード": "54",
      "競輪場名": "向日町",
      "開催名": "みんなの競輪カップ　京蓮の花賞",
      "グレード": "F2",
      "レース番号": 9,
      "周長(m)": 400,
      "みなし直線(m)": 47.3,
      "カント角(度)": 30.4853,
      "レース種別": "Ａ級特選",
      "距離": 1625,
      "周回数": 4,
      "発走時刻": "14:52",
      "投票締切": "14:49",
      "天候": "晴",
      "風速": "2.7"
    },
    {
      "race_key": "20240719_向日町_10R",
      "開催日": "20240719",
      "競輪場コード": "54",
      "競輪場名": "向日町",
      "開催名": "みんなの競輪カップ　京蓮の花賞",
      "グレード": "F2",
      "レース番号": 10,
      "周長(m)": 400,
      "みなし直線(m)": 47.3,
      "カント角(度)": 30.4853,
      "レース種別": "Ａ級特選",
      "距離": 1625,
      "周回数": 4,
      "発走時刻": "15:24",
      "投票締切": "15:21",
      "天候": "晴",
      "風速": "2.2"
    },
    {
      "race_key": "20240719_向日町_11R",
      "開催日": "20240719",
      "競輪場コード": "54",
      "競輪場名": "向日町",
      "開催名": "みんなの競輪カップ　京蓮の花賞",
      "グレード": "F2",
      "レース番号": 11,
      "周長(m)": 400,
      "みなし直線(m)": 47.3,
      "カント角(度)": 30.4853,
      "レース種別": "Ａ級チ決勝",
      "距離": 1625,
      "周回数": 4,
      "発走時刻": "16:00",
      "投票締切": "15:57",
      "天候": "晴",
      "風速": "2.2"
    },
    {
      "race_key": "20240719_向日町_12R",
      "開催日": "20240719",
      "競輪場コード": "54",
      "競輪場名": "向日町",
      "開催名": "みんなの競輪カップ　京蓮の花賞",
      "グレード": "F2",
      "レース番号": 12,
      "周長(m)": 400,
      "みなし直線(m)": 47.3,
      "カント角(度)": 30.4853,
      "レース種別": "Ａ級決勝",
      "距離": 1625,
      "周回数": 4,
      "発走時刻": "16:40",
      "投票締切": "16:37",
      "天候": "晴",
      "風速": "1.8"
    },
    {
      "race_key": "20240719_高松_1R",
      "開催日": "20240719",
      "競輪場コード": "71",
      "競輪場名": "高松",
      "開催名": "やっぱ！オズパ！杯",
      "グレード": "F2",
      "レース番号": 1,
      "周長(m)": 400,
      "みなし直線(m)": 54.8,
      "カント角(度)": 33.2639,
      "レース種別": "Ａ級チ一般",
      "距離": 1625,
      "周回数": 4,
      "発走時刻": "08:30",
      "投票締切": "08:27",
      "天候": "晴",
      "風速": "0.4"
    },
    {
      "race_key": "20240719_高松_2R",
      "開催日": "20240719",
      "競輪場コード": "71",
      "競輪場名": "高松",
      "開催名": "やっぱ！オズパ！杯",
      "グレード": "F2",
      "レース番号": 2,
      "周長(m)": 400,
      "みなし直線(m)": 54.8,
      "カント角(度)": 33.2639,
      "レース種別": "Ａ級チ一般",
      "距離": 1625,
      "周回数": 4,
      "発走時刻": "08:50",
      "投票締切": "08:47",
      "天候": "晴",
      "風速": "0.9"
    },
    {
      "race_key": "20240719_高松_3R",
      "開催日": "20240719",
      "競輪場コード": "71",
      "競輪場名": "高松",
      "開催名": "やっぱ！オズパ！杯",
      "グレード": "F2",
      "レース番号": 3,
      "周長(m)": 400,
      "みなし直線(m)": 54.8,
      "カント角(度)": 33.2639,
      "レース種別": "Ａ級チ準決",
      "距離": 1625,
      "周回数": 4,
      "発走時刻": "09:10",
      "投票締切": "09:07",
      "天候": "晴",
      "風速": "0.9"
    },
    {
      "race_key": "20240719_高松_4R",
      "開催日": "20240719",
      "競輪場コード": "71",
      "競輪場名": "高松",
      "開催名": "やっぱ！オズパ！杯",
      "グレード": "F2",
      "レース番号": 4,
      "周長(m)": 400,
      "みなし直線(m)": 54.8,
      "カント角(度)": 33.2639,
      "レース種別": "Ａ級チ準決",
      "距離": 1625,
      "周回数": 4,
      "発走時刻": "09:30",
      "投票締切": "09:27",
      "天候": "晴",
      "風速": "1.3"
    },
    {
      "race_key": "20240719_高松_5R",
      "開催日": "20240719",
      "競輪場コード": "71",
      "競輪場名": "高松",
      "開催名": "やっぱ！オズパ！杯",
      "グレード": "F2",
      "レース番号": 5,
      "周長(m)": 400,
      "みなし直線(m)": 54.8,
      "カント角(度)": 33.2639,
      "レース種別": "Ａ級チ準決",
      "距離": 1625,
      "周回数": 4,
      "発走時刻": "09:50",
      "投票締切": "09:47",
      "天候": "晴",
      "風速": "1.3"
    },
    {
      "race_key": "20240719_高松_6R",
      "開催日": "20240719",
      "競輪場コード": "71",
      "競輪場名": "高松",
      "開催名": "やっぱ！オズパ！杯",
      "グレード": "F2",
      "レース番号": 6,
      "周長(m)": 400,
      "みなし直線(m)": 54.8,
      "カント角(度)": 33.2639,
      "レース種別": "Ｌ級ガ予２",
      "距離": 1625,
      "周回数": 4,
      "発走時刻": "10:10",
      "投票締切": "10:07",
      "天候": "晴",
      "風速": "1.3"
    },
    {
      "race_key": "20240719_高松_7R",
      "開催日": "20240719",
      "競輪場コード": "71",
      "競輪場名": "高松",
      "開催名": "やっぱ！オズパ！杯",
      "グレード": "F2",
      "レース番号": 7,
      "周長(m)": 400,
      "みなし直線(m)": 54.8,
      "カント角(度)": 33.2639,
      "レース種別": "Ｌ級ガ予２",
      "距離": 1625,
      "周回数": 4,
      "発走時刻": "10:30",
      "投票締切": "10:27",
      "天候": "晴",
      "風速": "1.3"
    },
    {
      "race_key": "20240719_高知_1R",
      "開催日": "20240719",
      "競輪場コード": "74",
      "競輪場名": "高知",
      "開催名": "よさこいナイター・ＣＴＣ杯",
      "グレード": "F2",
      "レース番号": 1,
      "周長(m)": 500,
      "みなし直線(m)": 52,
      "カント角(度)": 24.4975,
      "レース種別": "Ａ級チ一般",
      "距離": 1500,
      "周回数": 3,
      "発走時刻": "15:18",
      "投票締切": "15:15",
      "天候": "曇",
      "風速": "1.0"
    },
    {
      "race_key": "20240719_高知_2R",
      "開催日": "20240719",
      "競輪場コード": "74",
      "競輪場名": "高知",
      "開催名": "よさこいナイター・ＣＴＣ杯",
      "グレード": "F2",
      "レース番号": 2,
      "周長(m)": 500,
      "みなし直線(m)": 52,
      "カント角(度)": 24.4975,
      "レース種別": "Ａ級チ一般",
      "距離": 1500,
      "周回数": 3,
      "発走時刻": "15:43",
      "投票締切": "15:40",
      "天候": "曇",
      "風速": "1.0"
    },
    {
      "race_key": "20240719_高知_3R",
      "開催日": "20240719",
      "競輪場コード": "74",
      "競輪場名": "高知",
      "開催名": "よさこいナイター・ＣＴＣ杯",
      "グレード": "F2",
      "レース番号": 3,
      "周長(m)": 500,
      "みなし直線(m)": 52,
      "カント角(度)": 24.4975,
      "レース種別": "Ａ級チ準決",
      "距離": 1500,
      "周回数": 3,
      "発走時刻": "16:08",
      "投票締切": "16:05",
      "天候": "曇",
      "風速": "1.0"
    },
    {
      "race_key": "20240719_高知_4R",
      "開催日": "20240719",
      "競輪場コード": "74",
      "競輪場名": "高知",
      "開催名": "よさこいナイター・ＣＴＣ杯",
      "グレード": "F2",
      "レース番号": 4,
      "周長(m)": 500,
      "みなし直線(m)": 52,
      "カント角(度)": 24.4975,
      "レース種別": "Ａ級チ準決",
      "距離": 1500,
      "周回数": 3,
      "発走時刻": "16:33",
      "投票締切": "16:30",
      "天候": "曇",
      "風速": "1.0"
    },
    {
      "race_key": "20240719_高知_5R",
      "開催日": "20240719",
      "競輪場コード": "74",
      "競輪場名": "高知",
      "開催名": "よさこいナイター・ＣＴＣ杯",
      "グレード": "F2",
      "レース番号": 5,
      "周長(m)": 500,
      "みなし直線(m)": 52,
      "カント角(度)": 24.4975,
      "レース種別": "Ａ級チ準決",
      "距離": 1500,
      "周回数": 3,
      "発走時刻": "16:59",
      "投票締切": "16:56",
      "天候": "曇",
      "風速": "1.0"
    },
    {
      "race_key": "20240719_高知_6R",
      "開催日": "20240719",
      "競輪場コード": "74",
      "競輪場名": "高知",
      "開催名": "よさこいナイター・ＣＴＣ杯",
      "グレード": "F2",
      "レース番号": 6,
      "周長(m)": 500,
      "みなし直線(m)": 52,
      "カント角(度)": 24.4975,
      "レース種別": "Ｌ級ガ予２",
      "距離": 1500,
      "周回数": 3,
      "発走時刻": "17:25",
      "投票締切": "17:22",
      "天候": "曇",
      "風速": "1.0"
    },
    {
      "race_key": "20240719_高知_7R",
      "開催日": "20240719",
      "競輪場コード": "74",
      "競輪場名": "高知",
      "開催名": "よさこいナイター・ＣＴＣ杯",
      "グレード": "F2",
      "レース番号": 7,
      "周長(m)": 500,
      "みなし直線(m)": 52,
      "カント角(度)": 24.4975,
      "レース種別": "Ｌ級ガ予２",
      "距離": 1500,
      "周回数": 3,
      "発走時刻": "17:51",
      "投票締切": "17:48",
      "天候": "曇",
      "風速": "1.0"
    },
    {
      "race_key": "20240719_高知_8R",
      "開催日": "20240719",
      "競輪場コード": "74",
      "競輪場名": "高知",
      "開催名": "よさこいナイター・ＣＴＣ杯",
      "グレード": "F2",
      "レース番号": 8,
      "周長(m)": 500,
      "みなし直線(m)": 52,
      "カント角(度)": 24.4975,
      "レース種別": "Ａ級特一般",
      "距離": 1500,
      "周回数": 3,
      "発走時刻": "18:19",
      "投票締切": "18:16",
      "天候": "曇",
      "風速": "1.0"
    },
    {
      "race_key": "20240719_高知_9R",
      "開催日": "20240719",
      "競輪場コード": "74",
      "競輪場名": "高知",
      "開催名": "よさこいナイター・ＣＴＣ杯",
      "グレード": "F2",
      "レース番号": 9,
      "周長(m)": 500,
      "みなし直線(m)": 52,
      "カント角(度)": 24.4975,
      "レース種別": "Ａ級特一般",
      "距離": 1500,
      "周回数": 3,
      "発走時刻": "18:47",
      "投票締切": "18:44",
      "天候": "曇",
      "風速": "1.0"
    },
    {
      "race_key": "20240719_高知_10R",
      "開催日": "20240719",
      "競輪場コード": "74",
      "競輪場名": "高知",
      "開催名": "よさこいナイター・ＣＴＣ杯",
      "グレード": "F2",
      "レース番号": 10,
      "周長(m)": 500,
      "みなし直線(m)": 52,
      "カント角(度)": 24.4975,
      "レース種別": "Ａ級準決勝",
      "距離": 1500,
      "周回数": 3,
      "発走時刻": "19:17",
      "投票締切": "19:14",
      "天候": "曇",
      "風速": "1.0"
    },
    {
      "race_key": "20240719_高知_11R",
      "開催日": "20240719",
      "競輪場コード": "74",
      "競輪場名": "高知",
      "開催名": "よさこいナイター・ＣＴＣ杯",
      "グレード": "F2",
      "レース番号": 11,
      "周長(m)": 500,
      "みなし直線(m)": 52,
      "カント角(度)": 24.4975,
      "レース種別": "Ａ級準決勝",
      "距離": 1500,
      "周回数": 3,
      "発走時刻": "19:47",
      "投票締切": "19:44",
      "天候": "曇",
      "風速": "1.0"
    },
    {
      "race_key": "20240719_高知_12R",
      "開催日": "20240719",
      "競輪場コード": "74",
      "競輪場名": "高知",
      "開催名": "よさこいナイター・ＣＴＣ杯",
      "グレード": "F2",
      "レース番号": 12,
      "周長(m)": 500,
      "みなし直線(m)": 52,
      "カント角(度)": 24.4975,
      "レース種別": "Ａ級準決勝",
      "距離": 1500,
      "周回数": 3,
      "発走時刻": "20:18",
      "投票締切": "20:15",
      "天候": "曇",
      "風速": "1.0"
    }
  ]
}