{
  "target_date": "20251004",
  "venue_count": 8,
  "venues": [
    {
      "venue": "京王閣",
      "bank_code": "27",
      "encPrm": "2VJimz9EDEXUM2mIdkaXc97EJc0s2f6glx2v9aF4J40",
      "jsj001": {
        "C0201data": {
          "encSelParaK": "2VJimz9EDEXUM2mIdkaXc97EJc0s2f6glx2v9aF4J40",
          "encSelParaR": "2VJimz9EDEXUM2mIdkaXcwB2S3T4qVFyG6Xx3fEWwGc",
          "selKaisai": "20251004",
          "selKjyoCd": "27",
          "selRaceNo": 12,
          "encParaS": "2VJimz9EDEXUM2mIdkaXc5usGSBh4QwkAhU9V0zk_vc",
          "imgGradeSrc": "/pc/static/img/icon/grade/ico_g3.png",
          "imgGradeAlt": "G3",
          "raceName": "ゴールドカップレース",
          "joName": "京王閣競輪場",
          "imgFuka1Src": "/pc/static/img/icon/KaisaiIcon/ico_kaisaihuka_01.png",
          "imgFuka1Alt": "01",
          "imgFuka2Src": "",
          "imgFuka2Alt": "",
          "joInfo": "",
          "hhMessage": "",
          "flgRaceCancel": false,
          "flgSectionCancel": false,
          "cntRace": 0,
          "flgPrevBet": false,
          "cidPrevBetBgcolor": "zenjitu_hatubai_bg_color",
          "imgPushSrc": "",
          "imgPushAlt": "",
          "imgCongenialSrc": "",
          "imgCongenialAlt": "",
          "imgInterviewSrc": "/pc/static/img/icon/ico_film.png",
          "imgInterviewAlt": "ダイジェストボタン",
          "flgActvKekkaList": true,
          "flgRecodes": true,
          "flgActvSyumoku": true,
          "flgActvDugest": true,
          "flgActvSyutujyo": true,
          "flgLogin": false,
          "C0201ticker": [],
          "C0201kaisai": [
            {
              "txtEventDate": "10/02",
              "txtDaily": "(初日)",
              "encParaK": "2VJimz9EDEXUM2mIdkaXc5usGSBh4QwkAhU9V0zk_vc",
              "flgSelect": true
            },
            {
              "txtEventDate": "10/03",
              "txtDaily": "(2日目)",
              "encParaK": "2VJimz9EDEXUM2mIdkaXc2Tr67z2LJf9aAWzB6CMHgk",
              "flgSelect": true
            },
            {
              "txtEventDate": "10/04",
              "txtDaily": "(3日目)",
              "encParaK": "2VJimz9EDEXUM2mIdkaXc97EJc0s2f6glx2v9aF4J40",
              "flgSelect": true
            },
            {
              "txtEventDate": "10/05",
              "txtDaily": "(最終日)",
              "encParaK": "2VJimz9EDEXUM2mIdkaXcykculTL20UaW7Dt87vKVDA",
              "flgSelect": true
            }
          ],
          "C0201race": [
            {
              "flgRaceEnd": true,
              "flgActvRaceBtn": true,
              "encParaR": "2VJimz9EDEXUM2mIdkaXcyRGm9hxXzQSysMmv-3CLnY",
              "rcvKekka": "1",
              "rcvRefund": "1",
              "rcvOdds": "2"
            },
            {
              "flgRaceEnd": true,
              "flgActvRaceBtn": true,
              "encParaR": "2VJimz9EDEXUM2mIdkaXc0SaaOAYDOmjAmZ5yVtwkpA",
              "rcvKekka": "1",
              "rcvRefund": "1",
              "rcvOdds": "2"
            },
            {
              "flgRaceEnd": true,
              "flgActvRaceBtn": true,
              "encParaR": "2VJimz9EDEXUM2mIdkaXc8ZOb-llHc-zhr3TWbdNkuk",
              "rcvKekka": "1",
              "rcvRefund": "1",
              "rcvOdds": "2"
            },
            {
              "flgRaceEnd": true,
              "flgActvRaceBtn": true,
              "encParaR": "2VJimz9EDEXUM2mIdkaXc7UnOp_Fx35Cl9Fi7G12O20",
              "rcvKekka": "1",
              "rcvRefund": "1",
              "rcvOdds": "2"
            },
            {
              "flgRaceEnd": true,
              "flgActvRaceBtn": true,
              "encParaR": "2VJimz9EDEXUM2mIdkaXc4yC1b4n5hnA4G6B_QjLEjk",
              "rcvKekka": "1",
              "rcvRefund": "1",
              "rcvOdds": "2"
            },
            {
              "flgRaceEnd": true,
              "flgActvRaceBtn": true,
              "encParaR": "2VJimz9EDEXUM2mIdkaXcyyR1MEvJLy0_NlQtykWOXQ",
              "rcvKekka": "1",
              "rcvRefund": "1",
              "rcvOdds": "2"
            },
            {
              "flgRaceEnd": true,
              "flgActvRaceBtn": true,
              "encParaR": "2VJimz9EDEXUM2mIdkaXczlJVklUgU7qH8w0hg0SrOU",
              "rcvKekka": "1",
              "rcvRefund": "1",
              "rcvOdds": "2"
            },
            {
              "flgRaceEnd": true,
              "flgActvRaceBtn": true,
              "encParaR": "2VJimz9EDEXUM2mIdkaXc0tcZtyuzW3PTtEQ4q9jYnk",
              "rcvKekka": "1",
              "rcvRefund": "1",
              "rcvOdds": "2"
            },
            {
              "flgRaceEnd": true,
              "flgActvRaceBtn": true,
              "encParaR": "2VJimz9EDEXUM2mIdkaXc9c9LltGaLSUGtcTd8kyGcc",
              "rcvKekka": "1",
              "rcvRefund": "1",
              "rcvOdds": "2"
            },
            {
              "flgRaceEnd": true,
              "flgActvRaceBtn": true,
              "encParaR": "2VJimz9EDEXUM2mIdkaXc1_Dmb9dS6IKIDinMLu6cZE",
              "rcvKekka": "1",
              "rcvRefund": "1",
              "rcvOdds": "2"
            },
            {
              "flgRaceEnd": true,
              "flgActvRaceBtn": true,
              "encParaR": "2VJimz9EDEXUM2mIdkaXc_1SIpLur8aGd20_Dunyh9w",
              "rcvKekka": "1",
              "rcvRefund": "1",
              "rcvOdds": "2"
            },
            {
              "flgRaceEnd": true,
              "flgActvRaceBtn": true,
              "encParaR": "2VJimz9EDEXUM2mIdkaXcwB2S3T4qVFyG6Xx3fEWwGc",
              "rcvKekka": "1",
              "rcvRefund": "1",
              "rcvOdds": "2"
            }
          ],
          "C0201interview": [],
          "C0201racedtl": {
            "syumoku": "Ｓ級準決勝",
            "kyori": 2025,
            "syukai": 5,
            "nameKyosou": "先固",
            "aftStartTime": "16:18",
            "aftBetTime": "16:15",
            "bfrStartTime": "16:18",
            "bfrBetTime": "16:15",
            "flgViewPut": false,
            "C0201sensyu": [
              {
                "imgPlayerPictSrc": "/pc/dfw/portal/picture/sen01/sen0153/015349_00.jpg",
                "imgPlayerPictAlt": "寺沼",
                "cidCarNum": "base_color_1",
                "carNum": 1,
                "namePlayerSei": "寺沼",
                "numPlayer": "015349",
                "flgPush": false,
                "flgCongenial": false
              },
              {
                "imgPlayerPictSrc": "/pc/dfw/portal/picture/sen01/sen0147/014744_00.jpg",
                "imgPlayerPictAlt": "和田",
                "cidCarNum": "base_color_2",
                "carNum": 2,
                "namePlayerSei": "和田",
                "numPlayer": "014744",
                "flgPush": false,
                "flgCongenial": false
              },
              {
                "imgPlayerPictSrc": "/pc/dfw/portal/picture/sen01/sen0146/014681_00.jpg",
                "imgPlayerPictAlt": "松浦",
                "cidCarNum": "base_color_3",
                "carNum": 3,
                "namePlayerSei": "松浦",
                "numPlayer": "014681",
                "flgPush": false,
                "flgCongenial": false
              },
              {
                "imgPlayerPictSrc": "/pc/dfw/portal/picture/sen01/sen0150/015050_00.jpg",
                "imgPlayerPictAlt": "堀内",
                "cidCarNum": "base_color_4",
                "carNum": 4,
                "namePlayerSei": "堀内",
                "numPlayer": "015050",
                "flgPush": false,
                "flgCongenial": false
              },
              {
                "imgPlayerPictSrc": "/pc/dfw/portal/picture/sen01/sen0150/015090_00.jpg",
                "imgPlayerPictAlt": "高橋",
                "cidCarNum": "base_color_5",
                "carNum": 5,
                "namePlayerSei": "高橋",
                "numPlayer": "015090",
                "flgPush": false,
                "flgCongenial": false
              },
              {
                "imgPlayerPictSrc": "/pc/dfw/portal/picture/sen01/sen0142/014262_00.jpg",
                "imgPlayerPictAlt": "稲吉",
                "cidCarNum": "base_color_6",
                "carNum": 6,
                "namePlayerSei": "稲吉",
                "numPlayer": "014262",
                "flgPush": false,
                "flgCongenial": false
              },
              {
                "imgPlayerPictSrc": "/pc/dfw/portal/picture/sen01/sen0152/015242_00.jpg",
                "imgPlayerPictAlt": "眞杉",
                "cidCarNum": "base_color_7",
                "carNum": 7,
                "namePlayerSei": "眞杉",
                "numPlayer": "015242",
                "flgPush": false,
                "flgCongenial": false
              },
              {
                "imgPlayerPictSrc": "/pc/dfw/portal/picture/sen01/sen0126/012669_00.jpg",
                "imgPlayerPictAlt": "伊藤",
                "cidCarNum": "base_color_8",
                "carNum": 8,
                "namePlayerSei": "伊藤",
                "numPlayer": "012669",
                "flgPush": false,
                "flgCongenial": false
              },
              {
                "imgPlayerPictSrc": "/pc/dfw/portal/picture/sen01/sen0141/014182_00.jpg",
                "imgPlayerPictAlt": "大川",
                "cidCarNum": "base_color_9",
                "carNum": 9,
                "namePlayerSei": "大川",
                "numPlayer": "014182",
                "flgPush": false,
                "flgCongenial": false
              }
            ]
          }
        },
        "resultCd": 0,
        "writeANA": false
      }
    },
    {
      "venue": "川崎",
      "bank_code": "34",
      "encPrm": "AvUkM2BrloliE4equFivLU13KC1UgT2V2aUkPvBjVvM",
      "jsj001": {
        "C0201data": {
          "encSelParaK": "AvUkM2BrloliE4equFivLU13KC1UgT2V2aUkPvBjVvM",
          "encSelParaR": "AvUkM2BrloliE4equFivLUUhKLeXWDYz-YmmApe1ewE",
          "selKaisai": "20251004",
          "selKjyoCd": "34",
          "selRaceNo": 12,
          "encParaS": "AvUkM2BrloliE4equFivLfeJhB-cXONlxVv92PbSIIg",
          "imgGradeSrc": "/pc/static/img/icon/grade/ico_f1.png",
          "imgGradeAlt": "F1",
          "raceName": "オッズパーク杯",
          "joName": "川崎競輪場",
          "imgKkbnSrc": "/pc/static/img/icon/KaisaiIcon/ico_kaisai_3.png",
          "imgKkbnAlt": "3",
          "imgFuka1Src": "",
          "imgFuka1Alt": "",
          "imgFuka2Src": "",
          "imgFuka2Alt": "",
          "joInfo": "",
          "hhMessage": "",
          "flgRaceCancel": false,
          "flgSectionCancel": false,
          "cntRace": 0,
          "flgPrevBet": false,
          "cidPrevBetBgcolor": "zenjitu_hatubai_bg_color",
          "imgPushSrc": "",
          "imgPushAlt": "",
          "imgCongenialSrc": "",
          "imgCongenialAlt": "",
          "imgInterviewSrc": "/pc/static/img/icon/ico_film.png",
          "imgInterviewAlt": "ダイジェストボタン",
          "flgActvKekkaList": true,
          "flgRecodes": true,
          "flgActvSyumoku": true,
          "flgActvDugest": true,
          "flgActvSyutujyo": true,
          "flgLogin": false,
          "C0201ticker": [],
          "C0201kaisai": [
            {
              "txtEventDate": "10/03",
              "txtDaily": "(初日)",
              "encParaK": "AvUkM2BrloliE4equFivLfeJhB-cXONlxVv92PbSIIg",
              "flgSelect": true
            },
            {
              "txtEventDate": "10/04",
              "txtDaily": "(2日目)",
              "encParaK": "AvUkM2BrloliE4equFivLU13KC1UgT2V2aUkPvBjVvM",
              "flgSelect": true
            },
            {
              "txtEventDate": "10/05",
              "txtDaily": "(最終日)",
              "encParaK": "AvUkM2BrloliE4equFivLZeFuKavVwsa5gUmz25BgZw",
              "flgSelect": true
            }
          ],
          "C0201race": [
            {
              "flgRaceEnd": true,
              "flgActvRaceBtn": true,
              "encParaR": "AvUkM2BrloliE4equFivLYuAzII32tDTQ9EUHNEPGr4",
              "rcvKekka": "1",
              "rcvRefund": "1",
              "rcvOdds": "2"
            },
            {
              "flgRaceEnd": true,
              "flgActvRaceBtn": true,
              "encParaR": "AvUkM2BrloliE4equFivLSPpHU9ZwTwN2TgOkebSLqE",
              "rcvKekka": "1",
              "rcvRefund": "1",
              "rcvOdds": "2"
            },
            {
              "flgRaceEnd": true,
              "flgActvRaceBtn": true,
              "encParaR": "AvUkM2BrloliE4equFivLVlxYuCm8ykuW0lRPf-LmFw",
              "rcvKekka": "1",
              "rcvRefund": "1",
              "rcvOdds": "2"
            },
            {
              "flgRaceEnd": true,
              "flgActvRaceBtn": true,
              "encParaR": "AvUkM2BrloliE4equFivLa1lQ4ce2Bnes9-kwIej7_0",
              "rcvKekka": "1",
              "rcvRefund": "1",
              "rcvOdds": "2"
            },
            {
              "flgRaceEnd": true,
              "flgActvRaceBtn": true,
              "encParaR": "AvUkM2BrloliE4equFivLQKkKaFLjnyA12cW69Vqy6g",
              "rcvKekka": "1",
              "rcvRefund": "1",
              "rcvOdds": "2"
            },
            {
              "flgRaceEnd": true,
              "flgActvRaceBtn": true,
              "encParaR": "AvUkM2BrloliE4equFivLdSISFaD5IalVFo1MOFmYSU",
              "rcvKekka": "1",
              "rcvRefund": "1",
              "rcvOdds": "2"
            },
            {
              "flgRaceEnd": true,
              "flgActvRaceBtn": true,
              "encParaR": "AvUkM2BrloliE4equFivLegBCSFEG_WGXiETpO73wPE",
              "rcvKekka": "1",
              "rcvRefund": "1",
              "rcvOdds": "2"
            },
            {
              "flgRaceEnd": true,
              "flgActvRaceBtn": true,
              "encParaR": "AvUkM2BrloliE4equFivLcYZH8SYdUD_PUaPpC-PnNo",
              "rcvKekka": "1",
              "rcvRefund": "1",
              "rcvOdds": "2"
            },
            {
              "flgRaceEnd": true,
              "flgActvRaceBtn": true,
              "encParaR": "AvUkM2BrloliE4equFivLQbPTwkdM8mCVDisMTn4EyE",
              "rcvKekka": "1",
              "rcvRefund": "1",
              "rcvOdds": "2"
            },
            {
              "flgRaceEnd": true,
              "flgActvRaceBtn": true,
              "encParaR": "AvUkM2BrloliE4equFivLXyspNb663JqXCc6lBiUo6E",
              "rcvKekka": "1",
              "rcvRefund": "1",
              "rcvOdds": "2"
            },
            {
              "flgRaceEnd": true,
              "flgActvRaceBtn": true,
              "encParaR": "AvUkM2BrloliE4equFivLeTcCMTzjbJBhl9GkH0So14",
              "rcvKekka": "1",
              "rcvRefund": "1",
              "rcvOdds": "2"
            },
            {
              "flgRaceEnd": true,
              "flgActvRaceBtn": true,
              "encParaR": "AvUkM2BrloliE4equFivLUUhKLeXWDYz-YmmApe1ewE",
              "rcvKekka": "1",
              "rcvRefund": "1",
              "rcvOdds": "2"
            }
          ],
          "C0201interview": [
            {
              "interviewTitle": "S級優勝インタビュ",
              "daily": 1,
              "dailyBrunch": 1,
              "serialNumber": 1,
              "kDate": "20251003",
              "kJoCd": "34"
            }
          ],
          "C0201racedtl": {
            "syumoku": "Ｓ級準決勝",
            "kyori": 2025,
            "syukai": 5,
            "nameKyosou": "先固",
            "aftStartTime": "20:30",
            "aftBetTime": "20:27",
            "bfrStartTime": "20:30",
            "bfrBetTime": "20:27",
            "flgViewPut": false,
            "C0201sensyu": [
              {
                "imgPlayerPictSrc": "/pc/dfw/portal/picture/sen01/sen0140/014016_00.jpg",
                "imgPlayerPictAlt": "石塚",
                "cidCarNum": "base_color_1",
                "carNum": 1,
                "namePlayerSei": "石塚",
                "numPlayer": "014016",
                "flgPush": false,
                "flgCongenial": false
              },
              {
                "imgPlayerPictSrc": "/pc/dfw/portal/picture/sen01/sen0145/014554_00.jpg",
                "imgPlayerPictAlt": "山形",
                "cidCarNum": "base_color_2",
                "carNum": 2,
                "namePlayerSei": "山形",
                "numPlayer": "014554",
                "flgPush": false,
                "flgCongenial": false
              },
              {
                "imgPlayerPictSrc": "/pc/dfw/portal/picture/sen01/sen0148/014817_00.jpg",
                "imgPlayerPictAlt": "佐藤",
                "cidCarNum": "base_color_3",
                "carNum": 3,
                "namePlayerSei": "佐藤",
                "numPlayer": "014817",
                "flgPush": false,
                "flgCongenial": false
              },
              {
                "imgPlayerPictSrc": "/pc/dfw/portal/picture/sen01/sen0153/015385_00.jpg",
                "imgPlayerPictAlt": "立部",
                "cidCarNum": "base_color_4",
                "carNum": 4,
                "namePlayerSei": "立部",
                "numPlayer": "015385",
                "flgPush": false,
                "flgCongenial": false
              },
              {
                "imgPlayerPictSrc": "/pc/dfw/portal/picture/sen01/sen0154/015436_00.jpg",
                "imgPlayerPictAlt": "青野",
                "cidCarNum": "base_color_5",
                "carNum": 5,
                "namePlayerSei": "青野",
                "numPlayer": "015436",
                "flgPush": false,
                "flgCongenial": false
              },
              {
                "imgPlayerPictSrc": "/pc/dfw/portal/picture/sen01/sen0152/015254_00.jpg",
                "imgPlayerPictAlt": "鈴木",
                "cidCarNum": "base_color_6",
                "carNum": 6,
                "namePlayerSei": "鈴木",
                "numPlayer": "015254",
                "flgPush": false,
                "flgCongenial": false
              },
              {
                "imgPlayerPictSrc": "/pc/dfw/portal/picture/sen01/sen0141/014186_00.jpg",
                "imgPlayerPictAlt": "網谷",
                "cidCarNum": "base_color_7",
                "carNum": 7,
                "namePlayerSei": "網谷",
                "numPlayer": "014186",
                "flgPush": false,
                "flgCongenial": false
              }
            ]
          }
        },
        "resultCd": 0,
        "writeANA": false
      }
    },
    {
      "venue": "武雄",
      "bank_code": "84",
      "encPrm": "vi-WrCkePzB1GZAD4D9fVfWS0795o0oRfkN876d5tks",
      "jsj001": {
        "C0201data": {
          "encSelParaK": "vi-WrCkePzB1GZAD4D9fVfWS0795o0oRfkN876d5tks",
          "encSelParaR": "vi-WrCkePzB1GZAD4D9fVS-RuOvbv6vmoxUkTP6eF5I",
          "selKaisai": "20251004",
          "selKjyoCd": "84",
          "selRaceNo": 12,
          "encParaS": "vi-WrCkePzB1GZAD4D9fVd5AzTE5Dd7hSwjVsHTmi_E",
          "imgGradeSrc": "/pc/static/img/icon/grade/ico_f1.png",
          "imgGradeAlt": "F1",
          "raceName": "日本名輪会Ｃ佐々木昭彦杯",
          "joName": "武雄競輪場",
          "imgFuka1Src": "",
          "imgFuka1Alt": "",
          "imgFuka2Src": "",
          "imgFuka2Alt": "",
          "joInfo": "",
          "hhMessage": "",
          "flgRaceCancel": false,
          "flgSectionCancel": false,
          "cntRace": 0,
          "flgPrevBet": false,
          "cidPrevBetBgcolor": "zenjitu_hatubai_bg_color",
          "imgPushSrc": "",
          "imgPushAlt": "",
          "imgCongenialSrc": "",
          "imgCongenialAlt": "",
          "imgInterviewSrc": "/pc/static/img/icon/ico_film.png",
          "imgInterviewAlt": "ダイジェストボタン",
          "flgActvKekkaList": true,
          "flgRecodes": true,
          "flgActvSyumoku": true,
          "flgActvDugest": true,
          "flgActvSyutujyo": true,
          "flgLogin": false,
          "C0201ticker": [],
          "C0201kaisai": [
            {
              "txtEventDate": "10/02",
              "txtDaily": "(初日)",
              "encParaK": "vi-WrCkePzB1GZAD4D9fVd5AzTE5Dd7hSwjVsHTmi_E",
              "flgSelect": true
            },
            {
              "txtEventDate": "10/03",
              "txtDaily": "(2日目)",
              "encParaK": "vi-WrCkePzB1GZAD4D9fVd4MnNoxHZge-N17lHi1g4o",
              "flgSelect": true
            },
            {
              "txtEventDate": "10/04",
              "txtDaily": "(最終日)",
              "encParaK": "vi-WrCkePzB1GZAD4D9fVfWS0795o0oRfkN876d5tks",
              "flgSelect": true
            }
          ],
          "C0201race": [
            {
              "flgRaceEnd": true,
              "flgActvRaceBtn": true,
              "encParaR": "vi-WrCkePzB1GZAD4D9fVR3TRzTEvmyOAUPAAl3d8ec",
              "rcvKekka": "1",
              "rcvRefund": "1",
              "rcvOdds": "2"
            },
            {
              "flgRaceEnd": true,
              "flgActvRaceBtn": true,
              "encParaR": "vi-WrCkePzB1GZAD4D9fVXjo-25ruBiUP5ov5ccVEtM",
              "rcvKekka": "1",
              "rcvRefund": "1",
              "rcvOdds": "2"
            },
            {
              "flgRaceEnd": true,
              "flgActvRaceBtn": true,
              "encParaR": "vi-WrCkePzB1GZAD4D9fVZsym8QRxcVALS05nykr43E",
              "rcvKekka": "1",
              "rcvRefund": "1",
              "rcvOdds": "2"
            },
            {
              "flgRaceEnd": true,
              "flgActvRaceBtn": true,
              "encParaR": "vi-WrCkePzB1GZAD4D9fVUd-fdwiPPltp1Zd6QXBESA",
              "rcvKekka": "1",
              "rcvRefund": "1",
              "rcvOdds": "2"
            },
            {
              "flgRaceEnd": true,
              "flgActvRaceBtn": true,
              "encParaR": "vi-WrCkePzB1GZAD4D9fVXuk36N9fpw5h_lhbjGcssM",
              "rcvKekka": "1",
              "rcvRefund": "1",
              "rcvOdds": "2"
            },
            {
              "flgRaceEnd": true,
              "flgActvRaceBtn": true,
              "encParaR": "vi-WrCkePzB1GZAD4D9fVSQqnJN-fKu-sztHH6s_NRI",
              "rcvKekka": "1",
              "rcvRefund": "1",
              "rcvOdds": "2"
            },
            {
              "flgRaceEnd": true,
              "flgActvRaceBtn": true,
              "encParaR": "vi-WrCkePzB1GZAD4D9fVSrnlyHHGQ2MIEOcfiHF4JQ",
              "rcvKekka": "1",
              "rcvRefund": "1",
              "rcvOdds": "2"
            },
            {
              "flgRaceEnd": true,
              "flgActvRaceBtn": true,
              "encParaR": "vi-WrCkePzB1GZAD4D9fVSsqtmt0-19Nbl6sng_V4k0",
              "rcvKekka": "1",
              "rcvRefund": "1",
              "rcvOdds": "2"
            },
            {
              "flgRaceEnd": true,
              "flgActvRaceBtn": true,
              "encParaR": "vi-WrCkePzB1GZAD4D9fVdt9rPtxIGW6xuXjJ3WpekY",
              "rcvKekka": "1",
              "rcvRefund": "1",
              "rcvOdds": "2"
            },
            {
              "flgRaceEnd": true,
              "flgActvRaceBtn": true,
              "encParaR": "vi-WrCkePzB1GZAD4D9fVbMB_-oNG01TS25RYrPqZlk",
              "rcvKekka": "1",
              "rcvRefund": "1",
              "rcvOdds": "2"
            },
            {
              "flgRaceEnd": true,
              "flgActvRaceBtn": true,
              "encParaR": "vi-WrCkePzB1GZAD4D9fVbUf3_pNJPXMFKEt_adeBpc",
              "rcvKekka": "1",
              "rcvRefund": "1",
              "rcvOdds": "2"
            },
            {
              "flgRaceEnd": true,
              "flgActvRaceBtn": true,
              "encParaR": "vi-WrCkePzB1GZAD4D9fVS-RuOvbv6vmoxUkTP6eF5I",
              "rcvKekka": "1",
              "rcvRefund": "1",
              "rcvOdds": "2"
            }
          ],
          "C0201interview": [],
          "C0201racedtl": {
            "syumoku": "Ｓ級決勝",
            "kyori": 2025,
            "syukai": 5,
            "nameKyosou": "先固",
            "aftStartTime": "16:02",
            "aftBetTime": "15:59",
            "bfrStartTime": "16:02",
            "bfrBetTime": "15:59",
            "flgViewPut": false,
            "C0201sensyu": [
              {
                "imgPlayerPictSrc": "/pc/dfw/portal/picture/sen01/sen0140/014047_00.jpg",
                "imgPlayerPictAlt": "山田",
                "cidCarNum": "base_color_1",
                "carNum": 1,
                "namePlayerSei": "山田",
                "numPlayer": "014047",
                "flgPush": false,
                "flgCongenial": false
              },
              {
                "imgPlayerPictSrc": "/pc/dfw/portal/picture/sen01/sen0145/014553_00.jpg",
                "imgPlayerPictAlt": "久米",
                "cidCarNum": "base_color_2",
                "carNum": 2,
                "namePlayerSei": "久米",
                "numPlayer": "014553",
                "flgPush": false,
                "flgCongenial": false
              },
              {
                "imgPlayerPictSrc": "/pc/dfw/portal/picture/sen01/sen0137/013745_00.jpg",
                "imgPlayerPictAlt": "中川",
                "cidCarNum": "base_color_3",
                "carNum": 3,
                "namePlayerSei": "中川",
                "numPlayer": "013745",
                "flgPush": false,
                "flgCongenial": false
              },
              {
                "imgPlayerPictSrc": "/pc/dfw/portal/picture/sen01/sen0147/014794_00.jpg",
                "imgPlayerPictAlt": "阿部",
                "cidCarNum": "base_color_4",
                "carNum": 4,
                "namePlayerSei": "阿部",
                "numPlayer": "014794",
                "flgPush": false,
                "flgCongenial": false
              },
              {
                "imgPlayerPictSrc": "/pc/dfw/portal/picture/sen01/sen0125/012596_00.jpg",
                "imgPlayerPictAlt": "志智",
                "cidCarNum": "base_color_5",
                "carNum": 5,
                "namePlayerSei": "志智",
                "numPlayer": "012596",
                "flgPush": false,
                "flgCongenial": false
              },
              {
                "imgPlayerPictSrc": "/pc/dfw/portal/picture/sen01/sen0140/014041_00.jpg",
                "imgPlayerPictAlt": "田中",
                "cidCarNum": "base_color_6",
                "carNum": 6,
                "namePlayerSei": "田中",
                "numPlayer": "014041",
                "flgPush": false,
                "flgCongenial": false
              },
              {
                "imgPlayerPictSrc": "/pc/dfw/portal/picture/sen01/sen0154/015476_00.jpg",
                "imgPlayerPictAlt": "緒方",
                "cidCarNum": "base_color_7",
                "carNum": 7,
                "namePlayerSei": "緒方",
                "numPlayer": "015476",
                "flgPush": false,
                "flgCongenial": false
              }
            ]
          }
        },
        "resultCd": 0,
        "writeANA": false
      }
    },
    {
      "venue": "函館",
      "bank_code": "11",
      "encPrm": "8vdVlO5IxwzRzvGxziu8NmbAWj4uzUACOR2D9THOgWE",
      "jsj001": {
        "C0201data": {
          "encSelParaK": "8vdVlO5IxwzRzvGxziu8NmbAWj4uzUACOR2D9THOgWE",
          "encSelParaR": "8vdVlO5IxwzRzvGxziu8NobOk4v7oBugUNel3wFJXWo",
          "selKaisai": "20251004",
          "selKjyoCd": "11",
          "selRaceNo": 11,
          "encParaS": "8vdVlO5IxwzRzvGxziu8NmbAWj4uzUACOR2D9THOgWE",
          "imgGradeSrc": "/pc/static/img/icon/grade/ico_f2.png",
          "imgGradeAlt": "F2",
          "raceName": "モーモータクシー杯＆Ｖ北海道Ｃ",
          "joName": "函館競輪場",
          "imgKkbnSrc": "/pc/static/img/icon/KaisaiIcon/ico_kaisai_3.png",
          "imgKkbnAlt": "3",
          "imgFuka1Src": "/pc/static/img/icon/KaisaiIcon/ico_kaisaihuka_02.png",
          "imgFuka1Alt": "02",
          "imgFuka2Src": "",
          "imgFuka2Alt": "",
          "joInfo": "",
          "hhMessage": "",
          "flgRaceCancel": false,
          "flgSectionCancel": false,
          "cntRace": 0,
          "flgPrevBet": false,
          "cidPrevBetBgcolor": "zenjitu_hatubai_bg_color",
          "imgPushSrc": "",
          "imgPushAlt": "",
          "imgCongenialSrc": "",
          "imgCongenialAlt": "",
          "imgInterviewSrc": "/pc/static/img/icon/ico_film.png",
          "imgInterviewAlt": "ダイジェストボタン",
          "flgActvKekkaList": true,
          "flgRecodes": true,
          "flgActvSyumoku": true,
          "flgActvDugest": true,
          "flgActvSyutujyo": true,
          "flgLogin": false,
          "C0201ticker": [],
          "C0201kaisai": [
            {
              "txtEventDate": "10/04",
              "txtDaily": "(初日)",
              "encParaK": "8vdVlO5IxwzRzvGxziu8NmbAWj4uzUACOR2D9THOgWE",
              "flgSelect": true
            },
            {
              "txtEventDate": "10/05",
              "txtDaily": "(2日目)",
              "encParaK": "8vdVlO5IxwzRzvGxziu8NoFAL9QdWdkHHf79vAoaIg0",
              "flgSelect": true
            },
            {
              "txtEventDate": "10/06",
              "txtDaily": "(最終日)",
              "encParaK": "8vdVlO5IxwzRzvGxziu8NkWPifbI_AYCLteaGVw5BLk",
              "flgSelect": true
            }
          ],
          "C0201race": [
            {
              "flgRaceEnd": true,
              "flgActvRaceBtn": true,
              "encParaR": "8vdVlO5IxwzRzvGxziu8Nuj9N_hQiEHsf2GpFwiGxGA",
              "rcvKekka": "1",
              "rcvRefund": "1",
              "rcvOdds": "2"
            },
            {
              "flgRaceEnd": true,
              "flgActvRaceBtn": true,
              "encParaR": "8vdVlO5IxwzRzvGxziu8Nj6kUXhvPpUEsu1YK4-iOm4",
              "rcvKekka": "1",
              "rcvRefund": "1",
              "rcvOdds": "2"
            },
            {
              "flgRaceEnd": true,
              "flgActvRaceBtn": true,
              "encParaR": "8vdVlO5IxwzRzvGxziu8NkbKPPXEZjNk7paIx9h1yTY",
              "rcvKekka": "1",
              "rcvRefund": "1",
              "rcvOdds": "2"
            },
            {
              "flgRaceEnd": true,
              "flgActvRaceBtn": true,
              "encParaR": "8vdVlO5IxwzRzvGxziu8NrL25C8oS0zH8DIFgo6ZRhk",
              "rcvKekka": "1",
              "rcvRefund": "1",
              "rcvOdds": "2"
            },
            {
              "flgRaceEnd": true,
              "flgActvRaceBtn": true,
              "encParaR": "8vdVlO5IxwzRzvGxziu8NuHHRvEOX8JIMrgb_MMye9A",
              "rcvKekka": "1",
              "rcvRefund": "1",
              "rcvOdds": "2"
            },
            {
              "flgRaceEnd": true,
              "flgActvRaceBtn": true,
              "encParaR": "8vdVlO5IxwzRzvGxziu8NoLkFn79fI990FHQxzPTc44",
              "rcvKekka": "1",
              "rcvRefund": "1",
              "rcvOdds": "2"
            },
            {
              "flgRaceEnd": true,
              "flgActvRaceBtn": true,
              "encParaR": "8vdVlO5IxwzRzvGxziu8NsU5gBSgN-I3oDuM5aoA-do",
              "rcvKekka": "1",
              "rcvRefund": "1",
              "rcvOdds": "2"
            },
            {
              "flgRaceEnd": true,
              "flgActvRaceBtn": true,
              "encParaR": "8vdVlO5IxwzRzvGxziu8Nge1UZ0rcyFwQZRL1OhjtwA",
              "rcvKekka": "1",
              "rcvRefund": "1",
              "rcvOdds": "2"
            },
            {
              "flgRaceEnd": true,
              "flgActvRaceBtn": true,
              "encParaR": "8vdVlO5IxwzRzvGxziu8NohkR0VVHdKUShzWgRXzkuc",
              "rcvKekka": "1",
              "rcvRefund": "1",
              "rcvOdds": "2"
            },
            {
              "flgRaceEnd": true,
              "flgActvRaceBtn": true,
              "encParaR": "8vdVlO5IxwzRzvGxziu8NpK1aQeMxTsrTPYf9qr2bJ8",
              "rcvKekka": "1",
              "rcvRefund": "1",
              "rcvOdds": "2"
            },
            {
              "flgRaceEnd": true,
              "flgActvRaceBtn": true,
              "encParaR": "8vdVlO5IxwzRzvGxziu8NobOk4v7oBugUNel3wFJXWo",
              "rcvKekka": "1",
              "rcvRefund": "1",
              "rcvOdds": "2"
            }
          ],
          "C0201interview": [],
          "C0201racedtl": {
            "syumoku": "Ａ級初特選",
            "kyori": 1625,
            "syukai": 4,
            "nameKyosou": "先固",
            "aftStartTime": "20:15",
            "aftBetTime": "20:12",
            "bfrStartTime": "20:15",
            "bfrBetTime": "20:12",
            "flgViewPut": false,
            "C0201sensyu": [
              {
                "imgPlayerPictSrc": "/pc/dfw/portal/picture/sen01/sen0131/013118_00.jpg",
                "imgPlayerPictAlt": "山内",
                "cidCarNum": "base_color_1",
                "carNum": 1,
                "namePlayerSei": "山内",
                "numPlayer": "013118",
                "flgPush": false,
                "flgCongenial": false
              },
              {
                "imgPlayerPictSrc": "/pc/dfw/portal/picture/sen01/sen0155/015519_00.jpg",
                "imgPlayerPictAlt": "小池",
                "cidCarNum": "base_color_2",
                "carNum": 2,
                "namePlayerSei": "小池",
                "numPlayer": "015519",
                "flgPush": false,
                "flgCongenial": false
              },
              {
                "imgPlayerPictSrc": "/pc/dfw/portal/picture/sen01/sen0154/015416_00.jpg",
                "imgPlayerPictAlt": "小笠原",
                "cidCarNum": "base_color_3",
                "carNum": 3,
                "namePlayerSei": "小笠原",
                "numPlayer": "015416",
                "flgPush": false,
                "flgCongenial": false
              },
              {
                "imgPlayerPictSrc": "/pc/dfw/portal/picture/sen01/sen0153/015366_00.jpg",
                "imgPlayerPictAlt": "張野",
                "cidCarNum": "base_color_4",
                "carNum": 4,
                "namePlayerSei": "張野",
                "numPlayer": "015366",
                "flgPush": false,
                "flgCongenial": false
              },
              {
                "imgPlayerPictSrc": "/pc/dfw/portal/picture/sen01/sen0135/013537_00.jpg",
                "imgPlayerPictAlt": "谷津田",
                "cidCarNum": "base_color_5",
                "carNum": 5,
                "namePlayerSei": "谷津田",
                "numPlayer": "013537",
                "flgPush": false,
                "flgCongenial": false
              },
              {
                "imgPlayerPictSrc": "/pc/dfw/portal/picture/sen01/sen0155/015526_00.jpg",
                "imgPlayerPictAlt": "梅田",
                "cidCarNum": "base_color_6",
                "carNum": 6,
                "namePlayerSei": "梅田",
                "numPlayer": "015526",
                "flgPush": false,
                "flgCongenial": false
              },
              {
                "imgPlayerPictSrc": "/pc/dfw/portal/picture/sen01/sen0142/014292_00.jpg",
                "imgPlayerPictAlt": "丸山",
                "cidCarNum": "base_color_7",
                "carNum": 7,
                "namePlayerSei": "丸山",
                "numPlayer": "014292",
                "flgPush": false,
                "flgCongenial": false
              }
            ]
          }
        },
        "resultCd": 0,
        "writeANA": false
      }
    },
    {
      "venue": "青森",
      "bank_code": "12",
      "encPrm": "ZnQJYL2GjvbOwhYKY6p0T54YQkCTvhPrP0r4IsDGQlQ",
      "jsj001": {
        "C0201data": {
          "encSelParaK": "ZnQJYL2GjvbOwhYKY6p0T54YQkCTvhPrP0r4IsDGQlQ",
          "encSelParaR": "ZnQJYL2GjvbOwhYKY6p0T0ovb6zbr6-A5M8wOboL3Yk",
          "selKaisai": "20251004",
          "selKjyoCd": "12",
          "selRaceNo": 7,
          "encParaS": "ZnQJYL2GjvbOwhYKY6p0TyH9VJHOJU9HFXJEmYnVgtQ",
          "imgGradeSrc": "/pc/static/img/icon/grade/ico_f2.png",
          "imgGradeAlt": "F2",
          "raceName": "ウィンチケットミッドナイト競輪",
          "joName": "青森競輪場",
          "imgKkbnSrc": "/pc/static/img/icon/KaisaiIcon/ico_kaisai_5.png",
          "imgKkbnAlt": "5",
          "imgFuka1Src": "",
          "imgFuka1Alt": "",
          "imgFuka2Src": "",
          "imgFuka2Alt": "",
          "joInfo": "",
          "hhMessage": "",
          "flgRaceCancel": false,
          "flgSectionCancel": false,
          "cntRace": 0,
          "flgPrevBet": false,
          "cidPrevBetBgcolor": "zenjitu_hatubai_bg_color",
          "imgPushSrc": "",
          "imgPushAlt": "",
          "imgCongenialSrc": "",
          "imgCongenialAlt": "",
          "imgInterviewSrc": "/pc/static/img/icon/ico_film.png",
          "imgInterviewAlt": "ダイジェストボタン",
          "flgActvKekkaList": true,
          "flgRecodes": true,
          "flgActvSyumoku": true,
          "flgActvDugest": true,
          "flgActvSyutujyo": true,
          "flgLogin": false,
          "C0201ticker": [],
          "C0201kaisai": [
            {
              "txtEventDate": "10/03",
              "txtDaily": "(初日)",
              "encParaK": "ZnQJYL2GjvbOwhYKY6p0TyH9VJHOJU9HFXJEmYnVgtQ",
              "flgSelect": true
            },
            {
              "txtEventDate": "10/04",
              "txtDaily": "(2日目)",
              "encParaK": "ZnQJYL2GjvbOwhYKY6p0T54YQkCTvhPrP0r4IsDGQlQ",
              "flgSelect": true
            },
            {
              "txtEventDate": "10/05",
              "txtDaily": "(最終日)",
              "encParaK": "ZnQJYL2GjvbOwhYKY6p0T6Zu8X8eyGWkkSTOwHlGpXY",
              "flgSelect": true
            }
          ],
          "C0201race": [
            {
              "flgRaceEnd": true,
              "flgActvRaceBtn": true,
              "encParaR": "ZnQJYL2GjvbOwhYKY6p0T2YavHwrlBevYGHLp-7H1sg",
              "rcvKekka": "1",
              "rcvRefund": "1",
              "rcvOdds": "2"
            },
            {
              "flgRaceEnd": true,
              "flgActvRaceBtn": true,
              "encParaR": "ZnQJYL2GjvbOwhYKY6p0T-uA9Z8JizAF6OqKIgoDvgs",
              "rcvKekka": "1",
              "rcvRefund": "1",
              "rcvOdds": "2"
            },
            {
              "flgRaceEnd": true,
              "flgActvRaceBtn": true,
              "encParaR": "ZnQJYL2GjvbOwhYKY6p0TyOIvK2ZgXFi3-P6UCLnvKM",
              "rcvKekka": "1",
              "rcvRefund": "1",
              "rcvOdds": "2"
            },
            {
              "flgRaceEnd": true,
              "flgActvRaceBtn": true,
              "encParaR": "ZnQJYL2GjvbOwhYKY6p0T4GohZ6qVFH0bWxrOP1nIwo",
              "rcvKekka": "1",
              "rcvRefund": "1",
              "rcvOdds": "2"
            },
            {
              "flgRaceEnd": true,
              "flgActvRaceBtn": true,
              "encParaR": "ZnQJYL2GjvbOwhYKY6p0T8MXys-jxZgfIzC1fTGKBl4",
              "rcvKekka": "1",
              "rcvRefund": "1",
              "rcvOdds": "2"
            },
            {
              "flgRaceEnd": true,
              "flgActvRaceBtn": true,
              "encParaR": "ZnQJYL2GjvbOwhYKY6p0T7nNz3RGoYoIEx3cekr9mg0",
              "rcvKekka": "1",
              "rcvRefund": "1",
              "rcvOdds": "2"
            },
            {
              "flgRaceEnd": true,
              "flgActvRaceBtn": true,
              "encParaR": "ZnQJYL2GjvbOwhYKY6p0T0ovb6zbr6-A5M8wOboL3Yk",
              "rcvKekka": "1",
              "rcvRefund": "1",
              "rcvOdds": "2"
            }
          ],
          "C0201interview": [],
          "C0201racedtl": {
            "syumoku": "Ａ級チ準決",
            "kyori": 1625,
            "syukai": 4,
            "nameKyosou": "先固",
            "aftStartTime": "23:21",
            "aftBetTime": "23:18",
            "bfrStartTime": "23:21",
            "bfrBetTime": "23:18",
            "flgViewPut": false,
            "C0201sensyu": [
              {
                "imgPlayerPictSrc": "/pc/dfw/portal/picture/sen01/sen0158/015870_00.jpg",
                "imgPlayerPictAlt": "畑崎",
                "cidCarNum": "base_color_1",
                "carNum": 1,
                "namePlayerSei": "畑崎",
                "numPlayer": "015870",
                "flgPush": false,
                "flgCongenial": false
              },
              {
                "imgPlayerPictSrc": "/pc/dfw/portal/picture/sen01/sen0153/015368_00.jpg",
                "imgPlayerPictAlt": "井坂",
                "cidCarNum": "base_color_2",
                "carNum": 2,
                "namePlayerSei": "井坂",
                "numPlayer": "015368",
                "flgPush": false,
                "flgCongenial": false
              },
              {
                "imgPlayerPictSrc": "/pc/dfw/portal/picture/sen01/sen0144/014425_00.jpg",
                "imgPlayerPictAlt": "前川",
                "cidCarNum": "base_color_3",
                "carNum": 3,
                "namePlayerSei": "前川",
                "numPlayer": "014425",
                "flgPush": false,
                "flgCongenial": false
              },
              {
                "imgPlayerPictSrc": "/pc/dfw/portal/picture/sen01/sen0140/014099_00.jpg",
                "imgPlayerPictAlt": "坂本",
                "cidCarNum": "base_color_4",
                "carNum": 4,
                "namePlayerSei": "坂本",
                "numPlayer": "014099",
                "flgPush": false,
                "flgCongenial": false
              },
              {
                "imgPlayerPictSrc": "/pc/dfw/portal/picture/sen01/sen0139/013905_00.jpg",
                "imgPlayerPictAlt": "藤原",
                "cidCarNum": "base_color_5",
                "carNum": 5,
                "namePlayerSei": "藤原",
                "numPlayer": "013905",
                "flgPush": false,
                "flgCongenial": false
              },
              {
                "imgPlayerPictSrc": "/pc/dfw/portal/picture/sen01/sen0132/013244_00.jpg",
                "imgPlayerPictAlt": "小林",
                "cidCarNum": "base_color_6",
                "carNum": 6,
                "namePlayerSei": "小林",
                "numPlayer": "013244",
                "flgPush": false,
                "flgCongenial": false
              },
              {
                "imgPlayerPictSrc": "/pc/dfw/portal/picture/sen01/sen0135/013509_00.jpg",
                "imgPlayerPictAlt": "明星",
                "cidCarNum": "base_color_7",
                "carNum": 7,
                "namePlayerSei": "明星",
                "numPlayer": "013509",
                "flgPush": false,
                "flgCongenial": false
              }
            ]
          }
        },
        "resultCd": 0,
        "writeANA": false
      }
    },
    {
      "venue": "奈良",
      "bank_code": "53",
      "encPrm": "kcv9vRY3BQhJPm4clm0Mgxqv3WJiNSR-mHSfCpwbHr8",
      "jsj001": {
        "C0201data": {
          "encSelParaK": "kcv9vRY3BQhJPm4clm0Mgxqv3WJiNSR-mHSfCpwbHr8",
          "encSelParaR": "kcv9vRY3BQhJPm4clm0MgxMQevdtQOyRs-hNXOHON1w",
          "selKaisai": "20251004",
          "selKjyoCd": "53",
          "selRaceNo": 7,
          "encParaS": "kcv9vRY3BQhJPm4clm0MgxmJs7Iy_xDWQxXethuV_XM",
          "imgGradeSrc": "/pc/static/img/icon/grade/ico_f2.png",
          "imgGradeAlt": "F2",
          "raceName": "大阪スポーツ杯・チャリロト賞",
          "joName": "奈良競輪場",
          "imgKkbnSrc": "/pc/static/img/icon/KaisaiIcon/ico_kaisai_5.png",
          "imgKkbnAlt": "5",
          "imgFuka1Src": "",
          "imgFuka1Alt": "",
          "imgFuka2Src": "",
          "imgFuka2Alt": "",
          "joInfo": "",
          "hhMessage": "",
          "flgRaceCancel": false,
          "flgSectionCancel": false,
          "cntRace": 0,
          "flgPrevBet": false,
          "cidPrevBetBgcolor": "zenjitu_hatubai_bg_color",
          "imgPushSrc": "",
          "imgPushAlt": "",
          "imgCongenialSrc": "",
          "imgCongenialAlt": "",
          "imgInterviewSrc": "/pc/static/img/icon/ico_film.png",
          "imgInterviewAlt": "ダイジェストボタン",
          "flgActvKekkaList": true,
          "flgRecodes": true,
          "flgActvSyumoku": true,
          "flgActvDugest": true,
          "flgActvSyutujyo": true,
          "flgLogin": false,
          "C0201ticker": [],
          "C0201kaisai": [
            {
              "txtEventDate": "10/03",
              "txtDaily": "(初日)",
              "encParaK": "kcv9vRY3BQhJPm4clm0MgxmJs7Iy_xDWQxXethuV_XM",
              "flgSelect": true
            },
            {
              "txtEventDate": "10/04",
              "txtDaily": "(2日目)",
              "encParaK": "kcv9vRY3BQhJPm4clm0Mgxqv3WJiNSR-mHSfCpwbHr8",
              "flgSelect": true
            },
            {
              "txtEventDate": "10/05",
              "txtDaily": "(最終日)",
              "encParaK": "kcv9vRY3BQhJPm4clm0MgxR8yBc52KRd_DOuiYOrrSk",
              "flgSelect": true
            }
          ],
          "C0201race": [
            {
              "flgRaceEnd": true,
              "flgActvRaceBtn": true,
              "encParaR": "kcv9vRY3BQhJPm4clm0Mg5Cd8bTDWX6_Ujl5x0fQVEk",
              "rcvKekka": "1",
              "rcvRefund": "1",
              "rcvOdds": "2"
            },
            {
              "flgRaceEnd": true,
              "flgActvRaceBtn": true,
              "encParaR": "kcv9vRY3BQhJPm4clm0Mg5mO_Mkg6D3dAp9-2D0Zld4",
              "rcvKekka": "1",
              "rcvRefund": "1",
              "rcvOdds": "2"
            },
            {
              "flgRaceEnd": true,
              "flgActvRaceBtn": true,
              "encParaR": "kcv9vRY3BQhJPm4clm0Mg_QUOg2Pc45SrLsuHfiNjgc",
              "rcvKekka": "1",
              "rcvRefund": "1",
              "rcvOdds": "2"
            },
            {
              "flgRaceEnd": true,
              "flgActvRaceBtn": true,
              "encParaR": "kcv9vRY3BQhJPm4clm0Mg3wJUuzgKlMK7BQIbMxDkvQ",
              "rcvKekka": "1",
              "rcvRefund": "1",
              "rcvOdds": "2"
            },
            {
              "flgRaceEnd": true,
              "flgActvRaceBtn": true,
              "encParaR": "kcv9vRY3BQhJPm4clm0Mg7XFFyHCfb_8RNpT-CDw9Mk",
              "rcvKekka": "1",
              "rcvRefund": "1",
              "rcvOdds": "2"
            },
            {
              "flgRaceEnd": true,
              "flgActvRaceBtn": true,
              "encParaR": "kcv9vRY3BQhJPm4clm0MgwE53WLwKE8PnChvePOEbS0",
              "rcvKekka": "1",
              "rcvRefund": "1",
              "rcvOdds": "2"
            },
            {
              "flgRaceEnd": true,
              "flgActvRaceBtn": true,
              "encParaR": "kcv9vRY3BQhJPm4clm0MgxMQevdtQOyRs-hNXOHON1w",
              "rcvKekka": "1",
              "rcvRefund": "1",
              "rcvOdds": "2"
            }
          ],
          "C0201interview": [],
          "C0201racedtl": {
            "syumoku": "Ａ級チ準決",
            "kyori": 1682,
            "syukai": 5,
            "nameKyosou": "先固",
            "aftStartTime": "23:30",
            "aftBetTime": "23:27",
            "bfrStartTime": "23:30",
            "bfrBetTime": "23:27",
            "flgViewPut": false,
            "C0201sensyu": [
              {
                "imgPlayerPictSrc": "/pc/dfw/portal/picture/sen01/sen0159/015907_00.jpg",
                "imgPlayerPictAlt": "上杉",
                "cidCarNum": "base_color_1",
                "carNum": 1,
                "namePlayerSei": "上杉",
                "numPlayer": "015907",
                "flgPush": false,
                "flgCongenial": false
              },
              {
                "imgPlayerPictSrc": "/pc/dfw/portal/picture/sen01/sen0157/015735_00.jpg",
                "imgPlayerPictAlt": "岡本",
                "cidCarNum": "base_color_2",
                "carNum": 2,
                "namePlayerSei": "岡本",
                "numPlayer": "015735",
                "flgPush": false,
                "flgCongenial": false
              },
              {
                "imgPlayerPictSrc": "/pc/dfw/portal/picture/sen01/sen0134/013434_00.jpg",
                "imgPlayerPictAlt": "石黒",
                "cidCarNum": "base_color_3",
                "carNum": 3,
                "namePlayerSei": "石黒",
                "numPlayer": "013434",
                "flgPush": false,
                "flgCongenial": false
              },
              {
                "imgPlayerPictSrc": "/pc/dfw/portal/picture/sen01/sen0151/015100_00.jpg",
                "imgPlayerPictAlt": "渡邊",
                "cidCarNum": "base_color_4",
                "carNum": 4,
                "namePlayerSei": "渡邊",
                "numPlayer": "015100",
                "flgPush": false,
                "flgCongenial": false
              },
              {
                "imgPlayerPictSrc": "/pc/dfw/portal/picture/sen01/sen0140/014021_00.jpg",
                "imgPlayerPictAlt": "森川",
                "cidCarNum": "base_color_5",
                "carNum": 5,
                "namePlayerSei": "森川",
                "numPlayer": "014021",
                "flgPush": false,
                "flgCongenial": false
              },
              {
                "imgPlayerPictSrc": "/pc/dfw/portal/picture/sen01/sen0137/013788_00.jpg",
                "imgPlayerPictAlt": "白崎",
                "cidCarNum": "base_color_6",
                "carNum": 6,
                "namePlayerSei": "白崎",
                "numPlayer": "013788",
                "flgPush": false,
                "flgCongenial": false
              },
              {
                "imgPlayerPictSrc": "/pc/dfw/portal/picture/sen01/sen0139/013998_00.jpg",
                "imgPlayerPictAlt": "桂馬",
                "cidCarNum": "base_color_7",
                "carNum": 7,
                "namePlayerSei": "桂馬",
                "numPlayer": "013998",
                "flgPush": false,
                "flgCongenial": false
              }
            ]
          }
        },
        "resultCd": 0,
        "writeANA": false
      }
    },
    {
      "venue": "防府",
      "bank_code": "63",
      "encPrm": "1lI6dWxsr9uJMJQNhAKtpzS5P3uf6r8LlH5bmWP7dTw",
      "jsj001": {
        "C0201data": {
          "encSelParaK": "1lI6dWxsr9uJMJQNhAKtpzS5P3uf6r8LlH5bmWP7dTw",
          "encSelParaR": "1lI6dWxsr9uJMJQNhAKtp34WRX8POeJT-5hi3GXgN_I",
          "selKaisai": "20251004",
          "selKjyoCd": "63",
          "selRaceNo": 7,
          "encParaS": "1lI6dWxsr9uJMJQNhAKtp3yylKXGINCcis9HlyFHYtU",
          "imgGradeSrc": "/pc/static/img/icon/grade/ico_f2.png",
          "imgGradeAlt": "F2",
          "raceName": "日本トーター杯",
          "joName": "防府競輪場",
          "imgKkbnSrc": "/pc/static/img/icon/KaisaiIcon/ico_kaisai_8.png",
          "imgKkbnAlt": "8",
          "imgFuka1Src": "",
          "imgFuka1Alt": "",
          "imgFuka2Src": "",
          "imgFuka2Alt": "",
          "joInfo": "",
          "hhMessage": "",
          "flgRaceCancel": false,
          "flgSectionCancel": false,
          "cntRace": 0,
          "flgPrevBet": false,
          "cidPrevBetBgcolor": "zenjitu_hatubai_bg_color",
          "imgPushSrc": "",
          "imgPushAlt": "",
          "imgCongenialSrc": "",
          "imgCongenialAlt": "",
          "imgInterviewSrc": "/pc/static/img/icon/ico_film.png",
          "imgInterviewAlt": "ダイジェストボタン",
          "flgActvKekkaList": true,
          "flgRecodes": true,
          "flgActvSyumoku": true,
          "flgActvDugest": true,
          "flgActvSyutujyo": true,
          "flgLogin": false,
          "C0201ticker": [],
          "C0201kaisai": [
            {
              "txtEventDate": "10/03",
              "txtDaily": "(初日)",
              "encParaK": "1lI6dWxsr9uJMJQNhAKtp3yylKXGINCcis9HlyFHYtU",
              "flgSelect": true
            },
            {
              "txtEventDate": "10/04",
              "txtDaily": "(2日目)",
              "encParaK": "1lI6dWxsr9uJMJQNhAKtpzS5P3uf6r8LlH5bmWP7dTw",
              "flgSelect": true
            },
            {
              "txtEventDate": "10/05",
              "txtDaily": "(最終日)",
              "encParaK": "1lI6dWxsr9uJMJQNhAKtp_nYdeplVBMOetnNyzOcs4M",
              "flgSelect": true
            }
          ],
          "C0201race": [
            {
              "flgRaceEnd": true,
              "flgActvRaceBtn": true,
              "encParaR": "1lI6dWxsr9uJMJQNhAKtp2f6CaNLCRM_gE9ChHdNhi8",
              "rcvKekka": "1",
              "rcvRefund": "1",
              "rcvOdds": "2"
            },
            {
              "flgRaceEnd": true,
              "flgActvRaceBtn": true,
              "encParaR": "1lI6dWxsr9uJMJQNhAKtp7lKFfcOZtT8vrtdpiRH0_E",
              "rcvKekka": "1",
              "rcvRefund": "1",
              "rcvOdds": "2"
            },
            {
              "flgRaceEnd": true,
              "flgActvRaceBtn": true,
              "encParaR": "1lI6dWxsr9uJMJQNhAKtpyOwnfTNn5Ou3YDiUvkzja4",
              "rcvKekka": "1",
              "rcvRefund": "1",
              "rcvOdds": "2"
            },
            {
              "flgRaceEnd": true,
              "flgActvRaceBtn": true,
              "encParaR": "1lI6dWxsr9uJMJQNhAKtp3VrU20jDtc4hzs93UJ_1SA",
              "rcvKekka": "1",
              "rcvRefund": "1",
              "rcvOdds": "2"
            },
            {
              "flgRaceEnd": true,
              "flgActvRaceBtn": true,
              "encParaR": "1lI6dWxsr9uJMJQNhAKtpx0SZY1uf9rXqq0dQgjuMSs",
              "rcvKekka": "1",
              "rcvRefund": "1",
              "rcvOdds": "2"
            },
            {
              "flgRaceEnd": true,
              "flgActvRaceBtn": true,
              "encParaR": "1lI6dWxsr9uJMJQNhAKtp1zt0QJyX7hQJuZDfeMIpGo",
              "rcvKekka": "1",
              "rcvRefund": "1",
              "rcvOdds": "2"
            },
            {
              "flgRaceEnd": true,
              "flgActvRaceBtn": true,
              "encParaR": "1lI6dWxsr9uJMJQNhAKtp34WRX8POeJT-5hi3GXgN_I",
              "rcvKekka": "1",
              "rcvRefund": "1",
              "rcvOdds": "2"
            }
          ],
          "C0201interview": [],
          "C0201racedtl": {
            "syumoku": "Ａ級準決勝",
            "kyori": 1682,
            "syukai": 5,
            "nameKyosou": "先固",
            "aftStartTime": "10:35",
            "aftBetTime": "10:32",
            "bfrStartTime": "10:35",
            "bfrBetTime": "10:32",
            "flgViewPut": false,
            "C0201sensyu": [
              {
                "imgPlayerPictSrc": "/pc/dfw/portal/picture/sen01/sen0135/013571_00.jpg",
                "imgPlayerPictAlt": "小林",
                "cidCarNum": "base_color_1",
                "carNum": 1,
                "namePlayerSei": "小林",
                "numPlayer": "013571",
                "flgPush": false,
                "flgCongenial": false
              },
              {
                "imgPlayerPictSrc": "/pc/dfw/portal/picture/sen01/sen0156/015651_00.jpg",
                "imgPlayerPictAlt": "中川",
                "cidCarNum": "base_color_2",
                "carNum": 2,
                "namePlayerSei": "中川",
                "numPlayer": "015651",
                "flgPush": false,
                "flgCongenial": false
              },
              {
                "imgPlayerPictSrc": "/pc/dfw/portal/picture/sen01/sen0140/014059_00.jpg",
                "imgPlayerPictAlt": "高塩",
                "cidCarNum": "base_color_3",
                "carNum": 3,
                "namePlayerSei": "高塩",
                "numPlayer": "014059",
                "flgPush": false,
                "flgCongenial": false
              },
              {
                "imgPlayerPictSrc": "/pc/dfw/portal/picture/sen01/sen0157/015781_00.jpg",
                "imgPlayerPictAlt": "齊藤",
                "cidCarNum": "base_color_4",
                "carNum": 4,
                "namePlayerSei": "齊藤",
                "numPlayer": "015781",
                "flgPush": false,
                "flgCongenial": false
              },
              {
                "imgPlayerPictSrc": "/pc/dfw/portal/picture/sen01/sen0153/015359_00.jpg",
                "imgPlayerPictAlt": "山口",
                "cidCarNum": "base_color_5",
                "carNum": 5,
                "namePlayerSei": "山口",
                "numPlayer": "015359",
                "flgPush": false,
                "flgCongenial": false
              },
              {
                "imgPlayerPictSrc": "/pc/dfw/portal/picture/sen01/sen0135/013556_00.jpg",
                "imgPlayerPictAlt": "山信田",
                "cidCarNum": "base_color_6",
                "carNum": 6,
                "namePlayerSei": "山信田",
                "numPlayer": "013556",
                "flgPush": false,
                "flgCongenial": false
              },
              {
                "imgPlayerPictSrc": "/pc/dfw/portal/picture/sen01/sen0134/013447_00.jpg",
                "imgPlayerPictAlt": "坂本",
                "cidCarNum": "base_color_7",
                "carNum": 7,
                "namePlayerSei": "坂本",
                "numPlayer": "013447",
                "flgPush": false,
                "flgCongenial": false
              }
            ]
          }
        },
        "resultCd": 0,
        "writeANA": false
      }
    },
    {
      "venue": "小松島",
      "bank_code": "73",
      "encPrm": "Ucro3UIpLny0gs-rDTa8mwUqhYvrKuVQrx1KCxXipZQ",
      "jsj001": {
        "C0201data": {
          "encSelParaK": "Ucro3UIpLny0gs-rDTa8mwUqhYvrKuVQrx1KCxXipZQ",
          "encSelParaR": "Ucro3UIpLny0gs-rDTa8m77sQC53x6DYN1dbCcF04JQ",
          "selKaisai": "20251004",
          "selKjyoCd": "73",
          "selRaceNo": 7,
          "encParaS": "Ucro3UIpLny0gs-rDTa8mw5qiB4jzU2hgVNfWe6Nl5Q",
          "imgGradeSrc": "/pc/static/img/icon/grade/ico_f2.png",
          "imgGradeAlt": "F2",
          "raceName": "こんばんはチャリロト杯",
          "joName": "小松島競輪場",
          "imgKkbnSrc": "/pc/static/img/icon/KaisaiIcon/ico_kaisai_5.png",
          "imgKkbnAlt": "5",
          "imgFuka1Src": "",
          "imgFuka1Alt": "",
          "imgFuka2Src": "",
          "imgFuka2Alt": "",
          "joInfo": "",
          "hhMessage": "",
          "flgRaceCancel": false,
          "flgSectionCancel": false,
          "cntRace": 0,
          "flgPrevBet": false,
          "cidPrevBetBgcolor": "zenjitu_hatubai_bg_color",
          "imgPushSrc": "",
          "imgPushAlt": "",
          "imgCongenialSrc": "",
          "imgCongenialAlt": "",
          "imgInterviewSrc": "/pc/static/img/icon/ico_film.png",
          "imgInterviewAlt": "ダイジェストボタン",
          "flgActvKekkaList": true,
          "flgRecodes": true,
          "flgActvSyumoku": true,
          "flgActvDugest": true,
          "flgActvSyutujyo": true,
          "flgLogin": false,
          "C0201ticker": [],
          "C0201kaisai": [
            {
              "txtEventDate": "10/03",
              "txtDaily": "(初日)",
              "encParaK": "Ucro3UIpLny0gs-rDTa8mw5qiB4jzU2hgVNfWe6Nl5Q",
              "flgSelect": true
            },
            {
              "txtEventDate": "10/04",
              "txtDaily": "(2日目)",
              "encParaK": "Ucro3UIpLny0gs-rDTa8mwUqhYvrKuVQrx1KCxXipZQ",
              "flgSelect": true
            },
            {
              "txtEventDate": "10/05",
              "txtDaily": "(最終日)",
              "encParaK": "Ucro3UIpLny0gs-rDTa8m2Shy4AeJ4BqQR41AxT4ack",
              "flgSelect": true
            }
          ],
          "C0201race": [
            {
              "flgRaceEnd": true,
              "flgActvRaceBtn": true,
              "encParaR": "Ucro3UIpLny0gs-rDTa8mxO5Jf3f79vuRIsVkg7w0Bc",
              "rcvKekka": "1",
              "rcvRefund": "1",
              "rcvOdds": "2"
            },
            {
              "flgRaceEnd": true,
              "flgActvRaceBtn": true,
              "encParaR": "Ucro3UIpLny0gs-rDTa8m_N8cSDKYj68nERlc3mOtgA",
              "rcvKekka": "1",
              "rcvRefund": "1",
              "rcvOdds": "2"
            },
            {
              "flgRaceEnd": true,
              "flgActvRaceBtn": true,
              "encParaR": "Ucro3UIpLny0gs-rDTa8m3b_7V20CjqMFv9-NsElXeg",
              "rcvKekka": "1",
              "rcvRefund": "1",
              "rcvOdds": "2"
            },
            {
              "flgRaceEnd": true,
              "flgActvRaceBtn": true,
              "encParaR": "Ucro3UIpLny0gs-rDTa8myZ-wc7iPvaKAB77Pi7JP9I",
              "rcvKekka": "1",
              "rcvRefund": "1",
              "rcvOdds": "2"
            },
            {
              "flgRaceEnd": true,
              "flgActvRaceBtn": true,
              "encParaR": "Ucro3UIpLny0gs-rDTa8m3Od3d0Uu4zcstEvv_L3nXw",
              "rcvKekka": "1",
              "rcvRefund": "1",
              "rcvOdds": "2"
            },
            {
              "flgRaceEnd": true,
              "flgActvRaceBtn": true,
              "encParaR": "Ucro3UIpLny0gs-rDTa8m_6myAXhsrBWbufErpY61CU",
              "rcvKekka": "1",
              "rcvRefund": "1",
              "rcvOdds": "2"
            },
            {
              "flgRaceEnd": true,
              "flgActvRaceBtn": true,
              "encParaR": "Ucro3UIpLny0gs-rDTa8m77sQC53x6DYN1dbCcF04JQ",
              "rcvKekka": "1",
              "rcvRefund": "1",
              "rcvOdds": "2"
            }
          ],
          "C0201interview": [],
          "C0201racedtl": {
            "syumoku": "Ａ級チ準決",
            "kyori": 1625,
            "syukai": 4,
            "nameKyosou": "先固",
            "aftStartTime": "23:12",
            "aftBetTime": "23:09",
            "bfrStartTime": "23:12",
            "bfrBetTime": "23:09",
            "flgViewPut": false,
            "C0201sensyu": [
              {
                "imgPlayerPictSrc": "/pc/dfw/portal/picture/sen01/sen0159/015926_00.jpg",
                "imgPlayerPictAlt": "諸隈",
                "cidCarNum": "base_color_1",
                "carNum": 1,
                "namePlayerSei": "諸隈",
                "numPlayer": "015926",
                "flgPush": false,
                "flgCongenial": false
              },
              {
                "imgPlayerPictSrc": "/pc/dfw/portal/picture/sen01/sen0146/014651_00.jpg",
                "imgPlayerPictAlt": "須永",
                "cidCarNum": "base_color_2",
                "carNum": 2,
                "namePlayerSei": "須永",
                "numPlayer": "014651",
                "flgPush": false,
                "flgCongenial": false
              },
              {
                "imgPlayerPictSrc": "/pc/dfw/portal/picture/sen01/sen0148/014841_00.jpg",
                "imgPlayerPictAlt": "井上",
                "cidCarNum": "base_color_3",
                "carNum": 3,
                "namePlayerSei": "井上",
                "numPlayer": "014841",
                "flgPush": false,
                "flgCongenial": false
              },
              {
                "imgPlayerPictSrc": "/pc/dfw/portal/picture/sen01/sen0129/012914_00.jpg",
                "imgPlayerPictAlt": "武市",
                "cidCarNum": "base_color_4",
                "carNum": 4,
                "namePlayerSei": "武市",
                "numPlayer": "012914",
                "flgPush": false,
                "flgCongenial": false
              },
              {
                "imgPlayerPictSrc": "/pc/dfw/portal/picture/sen01/sen0116/011665_00.jpg",
                "imgPlayerPictAlt": "倉岡",
                "cidCarNum": "base_color_5",
                "carNum": 5,
                "namePlayerSei": "倉岡",
                "numPlayer": "011665",
                "flgPush": false,
                "flgCongenial": false
              },
              {
                "imgPlayerPictSrc": "/pc/dfw/portal/picture/sen01/sen0137/013797_00.jpg",
                "imgPlayerPictAlt": "平川",
                "cidCarNum": "base_color_6",
                "carNum": 6,
                "namePlayerSei": "平川",
                "numPlayer": "013797",
                "flgPush": false,
                "flgCongenial": false
              },
              {
                "imgPlayerPictSrc": "/pc/dfw/portal/picture/sen01/sen0143/014357_00.jpg",
                "imgPlayerPictAlt": "佐藤",
                "cidCarNum": "base_color_7",
                "carNum": 7,
                "namePlayerSei": "佐藤",
                "numPlayer": "014357",
                "flgPush": false,
                "flgCongenial": false
              }
            ]
          }
        },
        "resultCd": 0,
        "writeANA": false
      }
    }
  ]
}