{
  "program": "001_collect_historical_schedule.py",
  "target_date": "20230703",
  "venue_count": 6,
  "venues": [
    {
      "競輪場コード": "12",
      "競輪場名": "青森",
      "encPrm": "jO_OtG-D_ngA1UTywZef2VUmnaq4RvTTMYgTrmDBMmU"
    },
    {
      "競輪場コード": "21",
      "競輪場名": "弥彦",
      "encPrm": "GUtJyf3wGjk1w1vpz6hOZjTq1mdk72-wbx86qpfgvx8"
    },
    {
      "競輪場コード": "44",
      "競輪場名": "大垣",
      "encPrm": "4J3_QrGuWsA9Lrls_uUdW0V9ZbvAMaEEsbEc_NGRpQQ"
    },
    {
      "競輪場コード": "71",
      "競輪場名": "高松",
      "encPrm": "D5HNE-3hivyoVTJmCCQDYBMLAuvfxyf5Z1_tRLIfiBQ"
    },
    {
      "競輪場コード": "74",
      "競輪場名": "高知",
      "encPrm": "N8bEsz6CQ53YTv16FsDHPm89KXVmrVx80ZZ8Q9Elck0"
    },
    {
      "競輪場コード": "84",
      "競輪場名": "武雄",
      "encPrm": "7KEG1-tbp4yqnEOvW46lxHRsy4TvgTVAmmAjWkBYTbQ"
    }
  ],
  "raw_jsj057": {
    "kInfo": [
      {
        "jyoName": "青森",
        "zenjituFlg": 0,
        "gradeIcon": "/pc/static/img/icon/grade/ico_f1.png",
        "gradeIconChar": "F1",
        "nitijiIcon": "/pc/static/img/icon/Himoku/ico_day2.png",
        "nitijiIconChar": "2日目",
        "kaisaiIcon": "/pc/static/img/icon/KaisaiIcon/ico_kaisai_3.png",
        "kaisaiIconChar": "3",
        "bgColor": "white_bg_color",
        "encPrm": "jO_OtG-D_ngA1UTywZef2VUmnaq4RvTTMYgTrmDBMmU",
        "bKeirinCd": "12",
        "KeirinCd": "12",
        "btnFlgLive": 1,
        "btnFlgOdds": 1,
        "btnFlgResult": 1,
        "btnFlgDokanto": 0,
        "btnFlgLiveDelivery": 0
      },
      {
        "jyoName": "弥彦",
        "zenjituFlg": 0,
        "gradeIcon": "/pc/static/img/icon/grade/ico_f1.png",
        "gradeIconChar": "F1",
        "nitijiIcon": "/pc/static/img/icon/Himoku/ico_day1.png",
        "nitijiIconChar": "初日",
        "kaisaiIcon": "/pc/static/img/icon/KaisaiIcon/ico_kaisai_1.png",
        "kaisaiIconChar": "1",
        "huka1Icon": "/pc/static/img/icon/KaisaiIcon/ico_kaisaihuka_01.png",
        "huka1IconChar": "01",
        "huka2Icon": "/pc/static/img/icon/KaisaiIcon/ico_kaisaihuka_02.png",
        "huka2IconChar": "02",
        "bgColor": "dokanto_color",
        "encPrm": "GUtJyf3wGjk1w1vpz6hOZjTq1mdk72-wbx86qpfgvx8",
        "bKeirinCd": "21",
        "KeirinCd": "21",
        "btnFlgLive": 1,
        "btnFlgOdds": 1,
        "btnFlgResult": 1,
        "btnFlgDokanto": 0,
        "btnFlgLiveDelivery": 0
      },
      {
        "jyoName": "大垣",
        "zenjituFlg": 0,
        "gradeIcon": "/pc/static/img/icon/grade/ico_f2.png",
        "gradeIconChar": "F2",
        "nitijiIcon": "/pc/static/img/icon/Himoku/ico_fday.png",
        "nitijiIconChar": "最終日",
        "kaisaiIcon": "/pc/static/img/icon/KaisaiIcon/ico_kaisai_5.png",
        "kaisaiIconChar": "5",
        "bgColor": "white_bg_color",
        "encPrm": "4J3_QrGuWsA9Lrls_uUdW0V9ZbvAMaEEsbEc_NGRpQQ",
        "bKeirinCd": "44",
        "KeirinCd": "44",
        "btnFlgLive": 1,
        "btnFlgOdds": 1,
        "btnFlgResult": 1,
        "btnFlgDokanto": 0,
        "btnFlgLiveDelivery": 0
      },
      {
        "jyoName": "高松",
        "zenjituFlg": 0,
        "gradeIcon": "/pc/static/img/icon/grade/ico_f2.png",
        "gradeIconChar": "F2",
        "nitijiIcon": "/pc/static/img/icon/Himoku/ico_day2.png",
        "nitijiIconChar": "2日目",
        "kaisaiIcon": "/pc/static/img/icon/KaisaiIcon/ico_kaisai_8.png",
        "kaisaiIconChar": "8",
        "bgColor": "white_bg_color",
        "encPrm": "D5HNE-3hivyoVTJmCCQDYBMLAuvfxyf5Z1_tRLIfiBQ",
        "bKeirinCd": "71",
        "KeirinCd": "71",
        "btnFlgLive": 1,
        "btnFlgOdds": 1,
        "btnFlgResult": 1,
        "btnFlgDokanto": 0,
        "btnFlgLiveDelivery": 0
      },
      {
        "jyoName": "高知",
        "zenjituFlg": 0,
        "gradeIcon": "/pc/static/img/icon/grade/ico_f2.png",
        "gradeIconChar": "F2",
        "nitijiIcon": "/pc/static/img/icon/Himoku/ico_fday.png",
        "nitijiIconChar": "最終日",
        "kaisaiIcon": "/pc/static/img/icon/KaisaiIcon/ico_kaisai_5.png",
        "kaisaiIconChar": "5",
        "huka1Icon": "/pc/static/img/icon/KaisaiIcon/ico_kaisaihuka_02.png",
        "huka1IconChar": "02",
        "bgColor": "white_bg_color",
        "encPrm": "N8bEsz6CQ53YTv16FsDHPm89KXVmrVx80ZZ8Q9Elck0",
        "bKeirinCd": "74",
        "KeirinCd": "74",
        "btnFlgLive": 1,
        "btnFlgOdds": 1,
        "btnFlgResult": 1,
        "btnFlgDokanto": 0,
        "btnFlgLiveDelivery": 0
      },
      {
        "jyoName": "武雄",
        "zenjituFlg": 0,
        "gradeIcon": "/pc/static/img/icon/grade/ico_f2.png",
        "gradeIconChar": "F2",
        "nitijiIcon": "/pc/static/img/icon/Himoku/ico_fday.png",
        "nitijiIconChar": "最終日",
        "kaisaiIcon": "/pc/static/img/icon/KaisaiIcon/ico_kaisai_5.png",
        "kaisaiIconChar": "5",
        "bgColor": "white_bg_color",
        "encPrm": "7KEG1-tbp4yqnEOvW46lxHRsy4TvgTVAmmAjWkBYTbQ",
        "bKeirinCd": "84",
        "KeirinCd": "84",
        "btnFlgLive": 1,
        "btnFlgOdds": 1,
        "btnFlgResult": 1,
        "btnFlgDokanto": 0,
        "btnFlgLiveDelivery": 0
      }
    ],
    "kResultCd": 1,
    "resultCd": 0,
    "reqprm": {
      "kday": "20230703"
    },
    "writeANA": false
  }
}